{"SK":{"dates":{"2020-05-23":{"delta":{"confirmed":1},"total":{"confirmed":1}},"2020-05-24":{"total":{"confirmed":1}},"2020-05-25":{"total":{"confirmed":1}},"2020-05-26":{"total":{"confirmed":1}},"2020-05-27":{"total":{"confirmed":1}},"2020-05-28":{"total":{"confirmed":1}},"2020-05-29":{"total":{"confirmed":1}},"2020-05-30":{"total":{"confirmed":1}},"2020-05-31":{"total":{"confirmed":1}},"2020-06-01":{"total":{"confirmed":1}},"2020-06-02":{"total":{"confirmed":1}},"2020-06-03":{"delta":{"confirmed":1},"total":{"confirmed":2}},"2020-06-04":{"total":{"confirmed":2}},"2020-06-05":{"delta":{"confirmed":1},"total":{"confirmed":3}},"2020-06-06":{"delta":{"confirmed":4},"total":{"confirmed":7}},"2020-06-07":{"total":{"confirmed":7}},"2020-06-08":{"total":{"confirmed":7}},"2020-06-09":{"delta":{"confirmed":6,"recovered":3},"total":{"confirmed":13,"recovered":3}},"2020-06-10":{"total":{"confirmed":13,"recovered":3}},"2020-06-11":{"total":{"confirmed":13,"recovered":3}},"2020-06-12":{"delta":{"confirmed":50},"total":{"confirmed":63,"recovered":3}},"2020-06-13":{"delta":{"recovered":1},"total":{"confirmed":63,"recovered":4}},"2020-06-14":{"delta":{"confirmed":5},"total":{"confirmed":68,"recovered":4}},"2020-06-15":{"total":{"confirmed":68,"recovered":4}},"2020-06-16":{"total":{"confirmed":68,"recovered":4}},"2020-06-17":{"delta":{"confirmed":2},"total":{"confirmed":70,"recovered":4}},"2020-06-18":{"delta":{"recovered":1},"total":{"confirmed":70,"recovered":5}},"2020-06-19":{"delta":{"recovered":16},"total":{"confirmed":70,"recovered":21}},"2020-06-20":{"total":{"confirmed":70,"recovered":21}},"2020-06-21":{"delta":{"confirmed":8,"recovered":4},"total":{"confirmed":78,"recovered":25}},"2020-06-22":{"delta":{"recovered":4},"total":{"confirmed":78,"recovered":29}},"2020-06-23":{"delta":{"confirmed":1},"total":{"confirmed":79,"recovered":29}},"2020-06-24":{"delta":{"confirmed":4,"recovered":10},"total":{"confirmed":83,"recovered":39}},"2020-06-25":{"delta":{"confirmed":2},"total":{"confirmed":85,"recovered":39}},"2020-06-26":{"delta":{"confirmed":2},"total":{"confirmed":87,"recovered":39}},"2020-06-27":{"delta":{"recovered":10},"total":{"confirmed":87,"recovered":49}},"2020-06-28":{"delta":{"confirmed":1},"total":{"confirmed":88,"recovered":49}},"2020-06-29":{"total":{"confirmed":88,"recovered":49}},"2020-06-30":{"delta":{"recovered":1},"total":{"confirmed":88,"recovered":50}},"2020-07-01":{"delta":{"confirmed":1,"recovered":2},"total":{"confirmed":89,"recovered":52}},"2020-07-02":{"delta":{"confirmed":12},"total":{"confirmed":101,"recovered":52}},"2020-07-03":{"delta":{"confirmed":1},"total":{"confirmed":102,"recovered":52}},"2020-07-04":{"delta":{"confirmed":1},"total":{"confirmed":103,"recovered":52}},"2020-07-05":{"delta":{"confirmed":22,"migrated":13,"recovered":9},"total":{"confirmed":125,"migrated":13,"recovered":61}},"2020-07-06":{"delta":{"recovered":4},"total":{"confirmed":125,"migrated":13,"recovered":65}},"2020-07-07":{"delta":{"confirmed":2},"total":{"confirmed":127,"migrated":13,"recovered":65}},"2020-07-08":{"delta":{"confirmed":6,"recovered":6},"total":{"confirmed":133,"migrated":13,"recovered":71}},"2020-07-09":{"delta":{"confirmed":1},"total":{"confirmed":134,"migrated":13,"recovered":71}},"2020-07-10":{"delta":{"recovered":9},"total":{"confirmed":134,"migrated":13,"recovered":80}},"2020-07-11":{"delta":{"confirmed":26},"total":{"confirmed":160,"migrated":13,"recovered":80}},"2020-07-12":{"delta":{"confirmed":4,"recovered":1},"total":{"confirmed":164,"migrated":13,"recovered":81}},"2020-07-13":{"delta":{"confirmed":2,"recovered":6},"total":{"confirmed":166,"migrated":13,"recovered":87}},"2020-07-14":{"delta":{"confirmed":45,"recovered":-1},"total":{"confirmed":211,"migrated":13,"recovered":86}},"2020-07-15":{"delta":{"confirmed":11,"recovered":1},"total":{"confirmed":222,"migrated":13,"recovered":87}},"2020-07-16":{"delta":{"confirmed":13},"total":{"confirmed":235,"migrated":13,"recovered":87}},"2020-07-17":{"delta":{"confirmed":32,"recovered":1},"total":{"confirmed":267,"migrated":13,"recovered":88}},"2020-07-18":{"delta":{"confirmed":19,"recovered":2},"total":{"confirmed":286,"migrated":13,"recovered":90}},"2020-07-19":{"delta":{"confirmed":10},"total":{"confirmed":296,"migrated":13,"recovered":90}},"2020-07-20":{"delta":{"confirmed":22,"recovered":2},"total":{"confirmed":318,"migrated":13,"recovered":92}},"2020-07-21":{"delta":{"confirmed":25,"recovered":16},"total":{"confirmed":343,"migrated":13,"recovered":108}},"2020-07-22":{"delta":{"confirmed":108,"recovered":4},"total":{"confirmed":451,"migrated":13,"recovered":112}},"2020-07-23":{"delta":{"confirmed":22,"recovered":10},"total":{"confirmed":473,"migrated":13,"recovered":122}},"2020-07-24":{"delta":{"confirmed":17,"recovered":15},"total":{"confirmed":490,"migrated":13,"recovered":137}},"2020-07-25":{"delta":{"confirmed":22,"recovered":5},"total":{"confirmed":512,"migrated":13,"recovered":142}}},"districts":{"East Sikkim":{"dates":{"2020-06-03":{"delta":{"confirmed":1},"total":{"confirmed":1}},"2020-06-04":{"total":{"confirmed":1}},"2020-06-05":{"delta":{"confirmed":1},"total":{"confirmed":2}},"2020-06-06":{"delta":{"confirmed":1},"total":{"confirmed":3}},"2020-06-07":{"total":{"confirmed":3}},"2020-06-08":{"total":{"confirmed":3}},"2020-06-09":{"delta":{"recovered":3},"total":{"confirmed":3,"recovered":3}},"2020-06-10":{"total":{"confirmed":3,"recovered":3}},"2020-06-11":{"total":{"confirmed":3,"recovered":3}},"2020-06-12":{"delta":{"confirmed":14},"total":{"confirmed":17,"recovered":3}},"2020-06-13":{"delta":{"confirmed":10,"recovered":1},"total":{"confirmed":27,"recovered":4}},"2020-06-14":{"delta":{"confirmed":-7},"total":{"confirmed":20,"recovered":4}},"2020-06-15":{"total":{"confirmed":20,"recovered":4}},"2020-06-16":{"total":{"confirmed":20,"recovered":4}},"2020-06-17":{"delta":{"confirmed":1},"total":{"confirmed":21,"recovered":4}},"2020-06-18":{"delta":{"recovered":1},"total":{"confirmed":21,"recovered":5}},"2020-06-19":{"delta":{"recovered":-3},"total":{"confirmed":21,"recovered":2}},"2020-06-20":{"total":{"confirmed":21,"recovered":2}},"2020-06-21":{"delta":{"confirmed":4},"total":{"confirmed":25,"recovered":2}},"2020-06-22":{"total":{"confirmed":25,"recovered":2}},"2020-06-23":{"total":{"confirmed":25,"recovered":2}},"2020-06-24":{"delta":{"recovered":1},"total":{"confirmed":25,"recovered":3}},"2020-06-25":{"delta":{"confirmed":1},"total":{"confirmed":26,"recovered":3}},"2020-06-26":{"delta":{"confirmed":1},"total":{"confirmed":27,"recovered":3}},"2020-06-27":{"delta":{"recovered":9},"total":{"confirmed":27,"recovered":12}},"2020-06-28":{"delta":{"confirmed":1},"total":{"confirmed":28,"recovered":12}},"2020-06-29":{"total":{"confirmed":28,"recovered":12}},"2020-06-30":{"total":{"confirmed":28,"recovered":12}},"2020-07-01":{"delta":{"confirmed":1},"total":{"confirmed":29,"recovered":12}},"2020-07-02":{"delta":{"confirmed":12,"recovered":2},"total":{"confirmed":41,"recovered":14}},"2020-07-03":{"total":{"confirmed":41,"recovered":14}},"2020-07-04":{"delta":{"confirmed":2},"total":{"confirmed":43,"recovered":14}},"2020-07-05":{"delta":{"confirmed":22,"migrated":13,"recovered":9},"total":{"confirmed":65,"migrated":13,"recovered":23}},"2020-07-06":{"delta":{"recovered":4},"total":{"confirmed":65,"migrated":13,"recovered":27}},"2020-07-07":{"delta":{"confirmed":2},"total":{"confirmed":67,"migrated":13,"recovered":27}},"2020-07-08":{"delta":{"confirmed":6,"recovered":6},"total":{"confirmed":73,"migrated":13,"recovered":33}},"2020-07-09":{"delta":{"confirmed":1},"total":{"confirmed":74,"migrated":13,"recovered":33}},"2020-07-10":{"delta":{"recovered":9},"total":{"confirmed":74,"migrated":13,"recovered":42}},"2020-07-11":{"delta":{"confirmed":26},"total":{"confirmed":100,"migrated":13,"recovered":42}},"2020-07-12":{"delta":{"confirmed":4,"recovered":1},"total":{"confirmed":104,"migrated":13,"recovered":43}},"2020-07-13":{"delta":{"confirmed":1,"recovered":6},"total":{"confirmed":105,"migrated":13,"recovered":49}},"2020-07-14":{"delta":{"confirmed":39,"recovered":-1},"total":{"confirmed":144,"migrated":13,"recovered":48}},"2020-07-15":{"delta":{"confirmed":11,"recovered":1},"total":{"confirmed":155,"migrated":13,"recovered":49}},"2020-07-16":{"delta":{"confirmed":13},"total":{"confirmed":168,"migrated":13,"recovered":49}},"2020-07-17":{"delta":{"confirmed":25,"recovered":1},"total":{"confirmed":193,"migrated":13,"recovered":50}},"2020-07-18":{"delta":{"confirmed":19,"recovered":2},"total":{"confirmed":212,"migrated":13,"recovered":52}},"2020-07-19":{"delta":{"confirmed":10},"total":{"confirmed":222,"migrated":13,"recovered":52}},"2020-07-20":{"delta":{"confirmed":22,"recovered":2},"total":{"confirmed":244,"migrated":13,"recovered":54}},"2020-07-21":{"delta":{"confirmed":24,"recovered":16},"total":{"confirmed":268,"migrated":13,"recovered":70}},"2020-07-22":{"delta":{"confirmed":61,"recovered":4},"total":{"confirmed":329,"migrated":13,"recovered":74}},"2020-07-23":{"delta":{"confirmed":19},"total":{"confirmed":348,"migrated":13,"recovered":74}},"2020-07-24":{"delta":{"confirmed":11},"total":{"confirmed":359,"migrated":13,"recovered":74}},"2020-07-25":{"total":{"confirmed":359,"migrated":13,"recovered":74}}}},"North Sikkim":{"dates":{"2020-06-26":{"delta":{"confirmed":1},"total":{"confirmed":1}},"2020-06-27":{"total":{"confirmed":1}},"2020-06-28":{"total":{"confirmed":1}},"2020-06-29":{"total":{"confirmed":1}},"2020-06-30":{"total":{"confirmed":1}},"2020-07-01":{"delta":{"recovered":1},"total":{"confirmed":1,"recovered":1}},"2020-07-02":{"total":{"confirmed":1,"recovered":1}},"2020-07-03":{"total":{"confirmed":1,"recovered":1}},"2020-07-04":{"total":{"confirmed":1,"recovered":1}},"2020-07-05":{"total":{"confirmed":1,"recovered":1}},"2020-07-06":{"total":{"confirmed":1,"recovered":1}},"2020-07-07":{"total":{"confirmed":1,"recovered":1}},"2020-07-08":{"total":{"confirmed":1,"recovered":1}},"2020-07-09":{"total":{"confirmed":1,"recovered":1}},"2020-07-10":{"total":{"confirmed":1,"recovered":1}},"2020-07-11":{"total":{"confirmed":1,"recovered":1}},"2020-07-12":{"total":{"confirmed":1,"recovered":1}},"2020-07-13":{"total":{"confirmed":1,"recovered":1}},"2020-07-14":{"total":{"confirmed":1,"recovered":1}},"2020-07-15":{"total":{"confirmed":1,"recovered":1}},"2020-07-16":{"total":{"confirmed":1,"recovered":1}},"2020-07-17":{"total":{"confirmed":1,"recovered":1}},"2020-07-18":{"total":{"confirmed":1,"recovered":1}},"2020-07-19":{"total":{"confirmed":1,"recovered":1}},"2020-07-20":{"total":{"confirmed":1,"recovered":1}},"2020-07-21":{"total":{"confirmed":1,"recovered":1}},"2020-07-22":{"total":{"confirmed":1,"recovered":1}},"2020-07-23":{"total":{"confirmed":1,"recovered":1}},"2020-07-24":{"total":{"confirmed":1,"recovered":1}},"2020-07-25":{"total":{"confirmed":1,"recovered":1}}}},"South Sikkim":{"dates":{"2020-05-23":{"delta":{"confirmed":1},"total":{"confirmed":1}},"2020-05-24":{"total":{"confirmed":1}},"2020-05-25":{"total":{"confirmed":1}},"2020-05-26":{"total":{"confirmed":1}},"2020-05-27":{"total":{"confirmed":1}},"2020-05-28":{"total":{"confirmed":1}},"2020-05-29":{"total":{"confirmed":1}},"2020-05-30":{"total":{"confirmed":1}},"2020-05-31":{"total":{"confirmed":1}},"2020-06-01":{"total":{"confirmed":1}},"2020-06-02":{"total":{"confirmed":1}},"2020-06-03":{"total":{"confirmed":1}},"2020-06-04":{"total":{"confirmed":1}},"2020-06-05":{"total":{"confirmed":1}},"2020-06-06":{"total":{"confirmed":1}},"2020-06-07":{"total":{"confirmed":1}},"2020-06-08":{"total":{"confirmed":1}},"2020-06-09":{"delta":{"confirmed":2},"total":{"confirmed":3}},"2020-06-10":{"total":{"confirmed":3}},"2020-06-11":{"total":{"confirmed":3}},"2020-06-12":{"total":{"confirmed":3}},"2020-06-13":{"delta":{"confirmed":20},"total":{"confirmed":23}},"2020-06-14":{"delta":{"confirmed":4},"total":{"confirmed":27}},"2020-06-15":{"total":{"confirmed":27}},"2020-06-16":{"total":{"confirmed":27}},"2020-06-17":{"total":{"confirmed":27}},"2020-06-18":{"total":{"confirmed":27}},"2020-06-19":{"delta":{"recovered":18},"total":{"confirmed":27,"recovered":18}},"2020-06-20":{"total":{"confirmed":27,"recovered":18}},"2020-06-21":{"delta":{"confirmed":4,"recovered":4},"total":{"confirmed":31,"recovered":22}},"2020-06-22":{"delta":{"recovered":4},"total":{"confirmed":31,"recovered":26}},"2020-06-23":{"total":{"confirmed":31,"recovered":26}},"2020-06-24":{"delta":{"confirmed":4},"total":{"confirmed":35,"recovered":26}},"2020-06-25":{"delta":{"confirmed":1},"total":{"confirmed":36,"recovered":26}},"2020-06-26":{"delta":{"confirmed":2},"total":{"confirmed":38,"recovered":26}},"2020-06-27":{"total":{"confirmed":38,"recovered":26}},"2020-06-28":{"total":{"confirmed":38,"recovered":26}},"2020-06-29":{"total":{"confirmed":38,"recovered":26}},"2020-06-30":{"total":{"confirmed":38,"recovered":26}},"2020-07-01":{"total":{"confirmed":38,"recovered":26}},"2020-07-02":{"total":{"confirmed":38,"recovered":26}},"2020-07-03":{"total":{"confirmed":38,"recovered":26}},"2020-07-04":{"total":{"confirmed":38,"recovered":26}},"2020-07-05":{"total":{"confirmed":38,"recovered":26}},"2020-07-06":{"total":{"confirmed":38,"recovered":26}},"2020-07-07":{"total":{"confirmed":38,"recovered":26}},"2020-07-08":{"total":{"confirmed":38,"recovered":26}},"2020-07-09":{"total":{"confirmed":38,"recovered":26}},"2020-07-10":{"total":{"confirmed":38,"recovered":26}},"2020-07-11":{"total":{"confirmed":38,"recovered":26}},"2020-07-12":{"total":{"confirmed":38,"recovered":26}},"2020-07-13":{"delta":{"confirmed":1},"total":{"confirmed":39,"recovered":26}},"2020-07-14":{"delta":{"confirmed":5},"total":{"confirmed":44,"recovered":26}},"2020-07-15":{"total":{"confirmed":44,"recovered":26}},"2020-07-16":{"total":{"confirmed":44,"recovered":26}},"2020-07-17":{"total":{"confirmed":44,"recovered":26}},"2020-07-18":{"total":{"confirmed":44,"recovered":26}},"2020-07-19":{"total":{"confirmed":44,"recovered":26}},"2020-07-20":{"total":{"confirmed":44,"recovered":26}},"2020-07-21":{"delta":{"confirmed":1},"total":{"confirmed":45,"recovered":26}},"2020-07-22":{"delta":{"confirmed":46},"total":{"confirmed":91,"recovered":26}},"2020-07-23":{"delta":{"recovered":10},"total":{"confirmed":91,"recovered":36}},"2020-07-24":{"delta":{"recovered":15},"total":{"confirmed":91,"recovered":51}},"2020-07-25":{"total":{"confirmed":91,"recovered":51}}}},"Unknown":{"dates":{"2020-06-09":{"delta":{"confirmed":3},"total":{"confirmed":3}},"2020-06-10":{"total":{"confirmed":3}},"2020-06-11":{"total":{"confirmed":3}},"2020-06-12":{"delta":{"confirmed":36},"total":{"confirmed":39}},"2020-06-13":{"delta":{"confirmed":-39}},"2020-06-14":{"delta":{"confirmed":1},"total":{"confirmed":1}},"2020-06-15":{"total":{"confirmed":1}},"2020-06-16":{"total":{"confirmed":1}},"2020-06-17":{"total":{"confirmed":1}},"2020-06-18":{"total":{"confirmed":1}},"2020-06-19":{"total":{"confirmed":1}},"2020-06-20":{"total":{"confirmed":1}},"2020-06-21":{"total":{"confirmed":1}},"2020-06-22":{"total":{"confirmed":1}},"2020-06-23":{"delta":{"confirmed":1},"total":{"confirmed":2}},"2020-06-24":{"total":{"confirmed":2}},"2020-06-25":{"total":{"confirmed":2}},"2020-06-26":{"delta":{"confirmed":-2}},"2020-07-01":{"delta":{"recovered":1},"total":{"recovered":1}},"2020-07-02":{"delta":{"recovered":-1}},"2020-07-03":{"delta":{"confirmed":1},"total":{"confirmed":1}},"2020-07-04":{"delta":{"confirmed":-1}},"2020-07-25":{"delta":{"confirmed":22,"recovered":5},"total":{"confirmed":22,"recovered":5}}}},"West Sikkim":{"dates":{"2020-06-06":{"delta":{"confirmed":3},"total":{"confirmed":3}},"2020-06-07":{"total":{"confirmed":3}},"2020-06-08":{"total":{"confirmed":3}},"2020-06-09":{"delta":{"confirmed":1},"total":{"confirmed":4}},"2020-06-10":{"total":{"confirmed":4}},"2020-06-11":{"total":{"confirmed":4}},"2020-06-12":{"total":{"confirmed":4}},"2020-06-13":{"delta":{"confirmed":9},"total":{"confirmed":13}},"2020-06-14":{"delta":{"confirmed":7},"total":{"confirmed":20}},"2020-06-15":{"total":{"confirmed":20}},"2020-06-16":{"total":{"confirmed":20}},"2020-06-17":{"delta":{"confirmed":1},"total":{"confirmed":21}},"2020-06-18":{"total":{"confirmed":21}},"2020-06-19":{"delta":{"recovered":1},"total":{"confirmed":21,"recovered":1}},"2020-06-20":{"total":{"confirmed":21,"recovered":1}},"2020-06-21":{"total":{"confirmed":21,"recovered":1}},"2020-06-22":{"total":{"confirmed":21,"recovered":1}},"2020-06-23":{"total":{"confirmed":21,"recovered":1}},"2020-06-24":{"delta":{"recovered":9},"total":{"confirmed":21,"recovered":10}},"2020-06-25":{"total":{"confirmed":21,"recovered":10}},"2020-06-26":{"total":{"confirmed":21,"recovered":10}},"2020-06-27":{"delta":{"recovered":1},"total":{"confirmed":21,"recovered":11}},"2020-06-28":{"total":{"confirmed":21,"recovered":11}},"2020-06-29":{"total":{"confirmed":21,"recovered":11}},"2020-06-30":{"delta":{"recovered":1},"total":{"confirmed":21,"recovered":12}},"2020-07-01":{"total":{"confirmed":21,"recovered":12}},"2020-07-02":{"delta":{"recovered":-1},"total":{"confirmed":21,"recovered":11}},"2020-07-03":{"total":{"confirmed":21,"recovered":11}},"2020-07-04":{"total":{"confirmed":21,"recovered":11}},"2020-07-05":{"total":{"confirmed":21,"recovered":11}},"2020-07-06":{"total":{"confirmed":21,"recovered":11}},"2020-07-07":{"total":{"confirmed":21,"recovered":11}},"2020-07-08":{"total":{"confirmed":21,"recovered":11}},"2020-07-09":{"total":{"confirmed":21,"recovered":11}},"2020-07-10":{"total":{"confirmed":21,"recovered":11}},"2020-07-11":{"total":{"confirmed":21,"recovered":11}},"2020-07-12":{"total":{"confirmed":21,"recovered":11}},"2020-07-13":{"total":{"confirmed":21,"recovered":11}},"2020-07-14":{"delta":{"confirmed":1},"total":{"confirmed":22,"recovered":11}},"2020-07-15":{"total":{"confirmed":22,"recovered":11}},"2020-07-16":{"total":{"confirmed":22,"recovered":11}},"2020-07-17":{"delta":{"confirmed":7},"total":{"confirmed":29,"recovered":11}},"2020-07-18":{"total":{"confirmed":29,"recovered":11}},"2020-07-19":{"total":{"confirmed":29,"recovered":11}},"2020-07-20":{"total":{"confirmed":29,"recovered":11}},"2020-07-21":{"total":{"confirmed":29,"recovered":11}},"2020-07-22":{"delta":{"confirmed":1},"total":{"confirmed":30,"recovered":11}},"2020-07-23":{"delta":{"confirmed":3},"total":{"confirmed":33,"recovered":11}},"2020-07-24":{"delta":{"confirmed":6},"total":{"confirmed":39,"recovered":11}},"2020-07-25":{"total":{"confirmed":39,"recovered":11}}}}}}}