{"NL":{"dates":{"2020-05-25":{"delta":{"confirmed":3},"total":{"confirmed":3}},"2020-05-26":{"delta":{"confirmed":1},"total":{"confirmed":4}},"2020-05-27":{"delta":{"confirmed":5},"total":{"confirmed":9}},"2020-05-28":{"delta":{"confirmed":9},"total":{"confirmed":18}},"2020-05-29":{"delta":{"confirmed":7},"total":{"confirmed":25}},"2020-05-30":{"delta":{"confirmed":11},"total":{"confirmed":36}},"2020-05-31":{"delta":{"confirmed":7},"total":{"confirmed":43}},"2020-06-01":{"total":{"confirmed":43}},"2020-06-02":{"delta":{"confirmed":6},"total":{"confirmed":49}},"2020-06-03":{"delta":{"confirmed":9},"total":{"confirmed":58}},"2020-06-04":{"delta":{"confirmed":22},"total":{"confirmed":80}},"2020-06-05":{"delta":{"confirmed":27},"total":{"confirmed":107}},"2020-06-06":{"delta":{"recovered":8},"total":{"confirmed":107,"recovered":8}},"2020-06-07":{"delta":{"confirmed":9},"total":{"confirmed":116,"recovered":8}},"2020-06-08":{"delta":{"confirmed":6},"total":{"confirmed":122,"recovered":8}},"2020-06-09":{"delta":{"confirmed":5,"recovered":2},"total":{"confirmed":127,"recovered":10}},"2020-06-10":{"delta":{"confirmed":1,"recovered":12},"total":{"confirmed":128,"recovered":22}},"2020-06-11":{"delta":{"confirmed":2,"recovered":7},"total":{"confirmed":130,"recovered":29}},"2020-06-12":{"delta":{"confirmed":26,"recovered":28},"total":{"confirmed":156,"recovered":57}},"2020-06-13":{"delta":{"confirmed":7,"recovered":27},"total":{"confirmed":163,"recovered":84}},"2020-06-14":{"delta":{"confirmed":10,"recovered":4},"total":{"confirmed":173,"recovered":88}},"2020-06-15":{"delta":{"confirmed":4},"total":{"confirmed":177,"recovered":88}},"2020-06-16":{"delta":{"confirmed":2,"recovered":15},"total":{"confirmed":179,"recovered":103}},"2020-06-17":{"delta":{"confirmed":14},"total":{"confirmed":193,"recovered":103}},"2020-06-18":{"delta":{"recovered":6},"total":{"confirmed":193,"recovered":109}},"2020-06-19":{"delta":{"confirmed":5,"recovered":16},"total":{"confirmed":198,"recovered":125}},"2020-06-20":{"delta":{"confirmed":3,"recovered":13},"total":{"confirmed":201,"recovered":138}},"2020-06-21":{"delta":{"confirmed":10,"recovered":3},"total":{"confirmed":211,"recovered":141}},"2020-06-22":{"delta":{"confirmed":69},"total":{"confirmed":280,"recovered":141}},"2020-06-23":{"delta":{"confirmed":50},"total":{"confirmed":330,"recovered":141}},"2020-06-24":{"delta":{"confirmed":17,"recovered":7},"total":{"confirmed":347,"recovered":148}},"2020-06-25":{"delta":{"confirmed":8,"recovered":12},"total":{"confirmed":355,"recovered":160}},"2020-06-26":{"delta":{"confirmed":16,"recovered":2},"total":{"confirmed":371,"recovered":162}},"2020-06-27":{"delta":{"confirmed":16,"recovered":2},"total":{"confirmed":387,"recovered":164}},"2020-06-28":{"delta":{"confirmed":28},"total":{"confirmed":415,"recovered":164}},"2020-06-29":{"delta":{"confirmed":36,"recovered":4},"total":{"confirmed":451,"recovered":168}},"2020-06-30":{"delta":{"confirmed":8},"total":{"confirmed":459,"recovered":168}},"2020-07-01":{"delta":{"confirmed":42,"recovered":14},"total":{"confirmed":501,"recovered":182}},"2020-07-02":{"delta":{"confirmed":34,"recovered":15},"total":{"confirmed":535,"recovered":197}},"2020-07-03":{"delta":{"confirmed":4,"recovered":31},"total":{"confirmed":539,"recovered":228}},"2020-07-04":{"delta":{"confirmed":24},"total":{"confirmed":563,"recovered":228}},"2020-07-05":{"delta":{"confirmed":27,"recovered":3},"total":{"confirmed":590,"recovered":231}},"2020-07-06":{"delta":{"confirmed":35,"recovered":12},"total":{"confirmed":625,"recovered":243}},"2020-07-07":{"delta":{"confirmed":19,"recovered":60},"total":{"confirmed":644,"recovered":303}},"2020-07-08":{"delta":{"confirmed":13,"recovered":1},"total":{"confirmed":657,"recovered":304}},"2020-07-09":{"delta":{"confirmed":16},"total":{"confirmed":673,"recovered":304}},"2020-07-10":{"delta":{"confirmed":59},"total":{"confirmed":732,"recovered":304}},"2020-07-11":{"delta":{"confirmed":16,"recovered":9},"total":{"confirmed":748,"recovered":313}},"2020-07-12":{"delta":{"confirmed":26,"recovered":14},"total":{"confirmed":774,"recovered":327}},"2020-07-13":{"delta":{"confirmed":71,"recovered":13},"total":{"confirmed":845,"recovered":340}},"2020-07-14":{"delta":{"confirmed":51,"recovered":6},"total":{"confirmed":896,"recovered":346}},"2020-07-15":{"delta":{"confirmed":6,"recovered":2},"total":{"confirmed":902,"recovered":348}},"2020-07-16":{"delta":{"confirmed":14,"recovered":43},"total":{"confirmed":916,"recovered":391}},"2020-07-17":{"delta":{"confirmed":40,"recovered":14},"total":{"confirmed":956,"recovered":405}},"2020-07-18":{"delta":{"confirmed":22,"recovered":27},"total":{"confirmed":978,"recovered":432}},"2020-07-19":{"delta":{"confirmed":10,"recovered":13},"total":{"confirmed":988,"recovered":445}},"2020-07-20":{"delta":{"confirmed":33,"recovered":39},"total":{"confirmed":1021,"recovered":484}},"2020-07-21":{"delta":{"confirmed":9,"recovered":1},"total":{"confirmed":1030,"recovered":485}},"2020-07-22":{"delta":{"confirmed":54,"recovered":1},"total":{"confirmed":1084,"recovered":486}},"2020-07-23":{"delta":{"confirmed":90,"recovered":44},"total":{"confirmed":1174,"recovered":530}},"2020-07-24":{"delta":{"confirmed":65,"deceased":1,"recovered":7},"total":{"confirmed":1239,"deceased":1,"recovered":537}},"2020-07-25":{"delta":{"confirmed":50,"deceased":3,"recovered":4},"total":{"confirmed":1289,"deceased":4,"recovered":541}},"2020-07-26":{"delta":{"confirmed":50,"recovered":8},"total":{"confirmed":1339,"deceased":4,"recovered":549}},"2020-07-27":{"delta":{"confirmed":46,"deceased":1,"recovered":20},"total":{"confirmed":1385,"deceased":5,"recovered":569}},"2020-07-28":{"delta":{"confirmed":75,"deceased":-1,"other":1,"recovered":8},"total":{"confirmed":1460,"deceased":4,"other":1,"recovered":577}},"2020-07-29":{"delta":{"confirmed":53,"recovered":18},"total":{"confirmed":1513,"deceased":4,"other":1,"recovered":595}},"2020-07-30":{"delta":{"confirmed":53,"other":1,"recovered":30},"total":{"confirmed":1566,"deceased":4,"other":2,"recovered":625}},"2020-07-31":{"delta":{"confirmed":127,"recovered":10},"total":{"confirmed":1693,"deceased":4,"other":2,"recovered":635}},"2020-08-01":{"delta":{"confirmed":138,"other":2,"recovered":5},"total":{"confirmed":1831,"deceased":4,"other":4,"recovered":640}},"2020-08-02":{"delta":{"confirmed":104,"recovered":8},"total":{"confirmed":1935,"deceased":4,"other":4,"recovered":648}},"2020-08-03":{"delta":{"confirmed":194,"recovered":9},"total":{"confirmed":2129,"deceased":4,"other":4,"recovered":657}},"2020-08-04":{"delta":{"confirmed":276,"recovered":2},"total":{"confirmed":2405,"deceased":4,"other":4,"recovered":659}},"2020-08-05":{"delta":{"confirmed":93,"deceased":2,"other":-1,"recovered":26},"total":{"confirmed":2498,"deceased":6,"other":3,"recovered":685}},"2020-08-06":{"delta":{"confirmed":82,"recovered":134},"total":{"confirmed":2580,"deceased":6,"other":3,"recovered":819}},"2020-08-07":{"delta":{"confirmed":77,"deceased":1,"other":-1,"recovered":5},"total":{"confirmed":2657,"deceased":7,"other":2,"recovered":824}},"2020-08-08":{"delta":{"confirmed":31,"other":1,"recovered":69},"total":{"confirmed":2688,"deceased":7,"other":3,"recovered":893}},"2020-08-09":{"delta":{"confirmed":93,"deceased":1,"recovered":11},"total":{"confirmed":2781,"deceased":8,"other":3,"recovered":904}},"2020-08-10":{"delta":{"confirmed":230,"recovered":69},"total":{"confirmed":3011,"deceased":8,"other":3,"recovered":973}},"2020-08-11":{"delta":{"confirmed":20,"deceased":-1,"other":4,"recovered":12},"total":{"confirmed":3031,"deceased":7,"other":7,"recovered":985}},"2020-08-12":{"delta":{"confirmed":87,"recovered":128},"total":{"confirmed":3118,"deceased":7,"other":7,"recovered":1113}},"2020-08-13":{"delta":{"confirmed":50,"recovered":26},"total":{"confirmed":3168,"deceased":7,"other":7,"recovered":1139}},"2020-08-14":{"delta":{"confirmed":154,"recovered":59},"total":{"confirmed":3322,"deceased":7,"other":7,"recovered":1198}},"2020-08-15":{"delta":{"confirmed":18,"recovered":123},"total":{"confirmed":3340,"deceased":7,"other":7,"recovered":1321}},"2020-08-16":{"delta":{"confirmed":54,"recovered":101},"total":{"confirmed":3394,"deceased":7,"other":7,"recovered":1422}},"2020-08-17":{"delta":{"confirmed":61,"recovered":108},"total":{"confirmed":3455,"deceased":7,"other":7,"recovered":1530}},"2020-08-18":{"delta":{"confirmed":65,"recovered":134},"total":{"confirmed":3520,"deceased":7,"other":7,"recovered":1664}}},"districts":{"Dimapur":{"dates":{"2020-05-19":{"delta":{"tested":722},"total":{"tested":722}},"2020-05-20":{"delta":{"tested":7},"total":{"tested":729}},"2020-05-21":{"total":{"tested":729}},"2020-05-22":{"delta":{"tested":13},"total":{"tested":742}},"2020-05-23":{"delta":{"tested":20},"total":{"tested":762}},"2020-05-24":{"delta":{"tested":15},"total":{"tested":777}},"2020-05-25":{"delta":{"confirmed":2},"total":{"confirmed":2,"tested":777}},"2020-05-26":{"delta":{"tested":80},"total":{"confirmed":2,"tested":857}},"2020-05-27":{"delta":{"confirmed":4,"tested":39},"total":{"confirmed":6,"tested":896}},"2020-05-28":{"delta":{"confirmed":6},"total":{"confirmed":12,"tested":896}},"2020-05-29":{"delta":{"confirmed":2},"total":{"confirmed":14,"tested":896}},"2020-05-30":{"delta":{"confirmed":8},"total":{"confirmed":22,"tested":896}},"2020-05-31":{"delta":{"confirmed":3},"total":{"confirmed":25,"tested":896}},"2020-06-01":{"total":{"confirmed":25,"tested":896}},"2020-06-02":{"delta":{"confirmed":6},"total":{"confirmed":31,"tested":896}},"2020-06-03":{"total":{"confirmed":31,"tested":896}},"2020-06-04":{"delta":{"confirmed":26},"total":{"confirmed":57,"tested":896}},"2020-06-05":{"total":{"confirmed":57,"tested":896}},"2020-06-06":{"delta":{"confirmed":-48,"recovered":8},"total":{"confirmed":9,"recovered":8,"tested":896}},"2020-06-07":{"delta":{"confirmed":11},"total":{"confirmed":20,"recovered":8,"tested":896}},"2020-06-08":{"delta":{"confirmed":-8},"total":{"confirmed":12,"recovered":8,"tested":896}},"2020-06-09":{"delta":{"confirmed":4},"total":{"confirmed":16,"recovered":8,"tested":896}},"2020-06-10":{"delta":{"recovered":4},"total":{"confirmed":16,"recovered":12,"tested":896}},"2020-06-11":{"delta":{"recovered":7},"total":{"confirmed":16,"recovered":19,"tested":896}},"2020-06-12":{"delta":{"confirmed":23,"recovered":8},"total":{"confirmed":39,"recovered":27,"tested":896}},"2020-06-13":{"delta":{"recovered":27},"total":{"confirmed":39,"recovered":54,"tested":896}},"2020-06-14":{"delta":{"confirmed":-16,"recovered":-54},"total":{"confirmed":23,"tested":896}},"2020-06-15":{"delta":{"confirmed":5},"total":{"confirmed":28,"tested":896}},"2020-06-16":{"total":{"confirmed":28,"tested":896}},"2020-06-17":{"delta":{"confirmed":1},"total":{"confirmed":29,"tested":896}},"2020-06-18":{"delta":{"recovered":4},"total":{"confirmed":29,"recovered":4,"tested":896}},"2020-06-19":{"delta":{"confirmed":1},"total":{"confirmed":30,"recovered":4,"tested":896}},"2020-06-20":{"total":{"confirmed":30,"recovered":4,"tested":896}},"2020-06-21":{"total":{"confirmed":30,"recovered":4,"tested":896}},"2020-06-22":{"delta":{"confirmed":3},"total":{"confirmed":33,"recovered":4,"tested":896}},"2020-06-23":{"delta":{"confirmed":24},"total":{"confirmed":57,"recovered":4,"tested":896}},"2020-06-24":{"delta":{"recovered":5},"total":{"confirmed":57,"recovered":9,"tested":896}},"2020-06-25":{"delta":{"confirmed":3,"recovered":8},"total":{"confirmed":60,"recovered":17,"tested":896}},"2020-06-26":{"total":{"confirmed":60,"recovered":17,"tested":896}},"2020-06-27":{"delta":{"confirmed":4,"recovered":2},"total":{"confirmed":64,"recovered":19,"tested":896}},"2020-06-28":{"delta":{"confirmed":20},"total":{"confirmed":84,"recovered":19,"tested":896}},"2020-06-29":{"total":{"confirmed":84,"recovered":19,"tested":896}},"2020-06-30":{"delta":{"confirmed":1},"total":{"confirmed":85,"recovered":19,"tested":896}},"2020-07-01":{"delta":{"confirmed":1},"total":{"confirmed":86,"recovered":19,"tested":896}},"2020-07-02":{"delta":{"confirmed":1},"total":{"confirmed":87,"recovered":19,"tested":896}},"2020-07-03":{"delta":{"recovered":10},"total":{"confirmed":87,"recovered":29,"tested":896}},"2020-07-04":{"total":{"confirmed":87,"recovered":29,"tested":896}},"2020-07-05":{"delta":{"confirmed":12},"total":{"confirmed":99,"recovered":29,"tested":896}},"2020-07-06":{"delta":{"confirmed":15},"total":{"confirmed":114,"recovered":29,"tested":896}},"2020-07-07":{"total":{"confirmed":114,"recovered":29,"tested":896}},"2020-07-08":{"delta":{"confirmed":9},"total":{"confirmed":123,"recovered":29,"tested":896}},"2020-07-09":{"total":{"confirmed":123,"recovered":29,"tested":896}},"2020-07-10":{"delta":{"confirmed":18},"total":{"confirmed":141,"recovered":29,"tested":896}},"2020-07-11":{"total":{"confirmed":141,"recovered":29,"tested":896}},"2020-07-12":{"delta":{"confirmed":18},"total":{"confirmed":159,"recovered":29,"tested":896}},"2020-07-13":{"delta":{"confirmed":60},"total":{"confirmed":219,"recovered":29,"tested":896}},"2020-07-14":{"delta":{"confirmed":3},"total":{"confirmed":222,"recovered":29,"tested":896}},"2020-07-15":{"delta":{"confirmed":6,"recovered":1},"total":{"confirmed":228,"recovered":30,"tested":896}},"2020-07-16":{"delta":{"confirmed":12},"total":{"confirmed":240,"recovered":30,"tested":896}},"2020-07-17":{"delta":{"confirmed":39},"total":{"confirmed":279,"recovered":30,"tested":896}},"2020-07-18":{"delta":{"confirmed":8},"total":{"confirmed":287,"recovered":30,"tested":896}},"2020-07-19":{"delta":{"confirmed":1},"total":{"confirmed":288,"recovered":30,"tested":896}},"2020-07-20":{"delta":{"confirmed":16},"total":{"confirmed":304,"recovered":30,"tested":896}},"2020-07-21":{"delta":{"confirmed":6},"total":{"confirmed":310,"recovered":30,"tested":896}},"2020-07-22":{"delta":{"confirmed":23},"total":{"confirmed":333,"recovered":30,"tested":896}},"2020-07-23":{"delta":{"confirmed":26,"recovered":33},"total":{"confirmed":359,"recovered":63,"tested":896}},"2020-07-24":{"delta":{"confirmed":41,"deceased":1},"total":{"confirmed":400,"deceased":1,"recovered":63,"tested":896}},"2020-07-25":{"delta":{"confirmed":19,"deceased":3,"recovered":-3},"total":{"confirmed":419,"deceased":4,"recovered":60,"tested":896}},"2020-07-26":{"delta":{"confirmed":9,"recovered":1},"total":{"confirmed":428,"deceased":4,"recovered":61,"tested":896}},"2020-07-27":{"delta":{"confirmed":14,"deceased":1,"recovered":4},"total":{"confirmed":442,"deceased":5,"recovered":65,"tested":896}},"2020-07-28":{"delta":{"confirmed":3,"deceased":-1,"other":1},"total":{"confirmed":445,"deceased":4,"other":1,"recovered":65,"tested":896}},"2020-07-29":{"delta":{"confirmed":29},"total":{"confirmed":474,"deceased":4,"other":1,"recovered":65,"tested":896}},"2020-07-30":{"delta":{"confirmed":32,"other":1},"total":{"confirmed":506,"deceased":4,"other":2,"recovered":65,"tested":896}},"2020-07-31":{"delta":{"confirmed":96},"total":{"confirmed":602,"deceased":4,"other":2,"recovered":65,"tested":896}},"2020-08-01":{"delta":{"confirmed":117,"other":1},"total":{"confirmed":719,"deceased":4,"other":3,"recovered":65,"tested":896}},"2020-08-02":{"delta":{"confirmed":62},"total":{"confirmed":781,"deceased":4,"other":3,"recovered":65,"tested":896}},"2020-08-03":{"delta":{"confirmed":136},"total":{"confirmed":917,"deceased":4,"other":3,"recovered":65,"tested":896}},"2020-08-04":{"delta":{"confirmed":187},"total":{"confirmed":1104,"deceased":4,"other":3,"recovered":65,"tested":896}},"2020-08-05":{"delta":{"confirmed":88,"deceased":2,"other":-1},"total":{"confirmed":1192,"deceased":6,"other":2,"recovered":65,"tested":896}},"2020-08-06":{"delta":{"confirmed":58,"recovered":88},"total":{"confirmed":1250,"deceased":6,"other":2,"recovered":153,"tested":896}},"2020-08-07":{"delta":{"confirmed":74},"total":{"confirmed":1324,"deceased":6,"other":2,"recovered":153,"tested":896}},"2020-08-08":{"delta":{"confirmed":10,"recovered":52},"total":{"confirmed":1334,"deceased":6,"other":2,"recovered":205,"tested":896}},"2020-08-09":{"delta":{"confirmed":62,"deceased":1},"total":{"confirmed":1396,"deceased":7,"other":2,"recovered":205,"tested":896}},"2020-08-10":{"delta":{"confirmed":104,"recovered":32},"total":{"confirmed":1500,"deceased":7,"other":2,"recovered":237,"tested":896}},"2020-08-11":{"delta":{"confirmed":9,"recovered":1},"total":{"confirmed":1509,"deceased":7,"other":2,"recovered":238,"tested":896}},"2020-08-12":{"delta":{"confirmed":48,"recovered":74},"total":{"confirmed":1557,"deceased":7,"other":2,"recovered":312,"tested":896}},"2020-08-13":{"delta":{"confirmed":1,"recovered":-1},"total":{"confirmed":1558,"deceased":7,"other":2,"recovered":311,"tested":896}},"2020-08-14":{"delta":{"confirmed":58,"recovered":38},"total":{"confirmed":1616,"deceased":7,"other":2,"recovered":349,"tested":896}},"2020-08-15":{"delta":{"recovered":54},"total":{"confirmed":1616,"deceased":7,"other":2,"recovered":403,"tested":896}},"2020-08-16":{"delta":{"confirmed":21,"recovered":57},"total":{"confirmed":1637,"deceased":7,"other":2,"recovered":460,"tested":896}},"2020-08-17":{"delta":{"confirmed":34,"recovered":72},"total":{"confirmed":1671,"deceased":7,"other":2,"recovered":532,"tested":896}},"2020-08-18":{"delta":{"confirmed":23,"recovered":79},"total":{"confirmed":1694,"deceased":7,"other":2,"recovered":611,"tested":896}}}},"Kiphire":{"dates":{"2020-05-26":{"delta":{"tested":18},"total":{"tested":18}},"2020-05-27":{"total":{"tested":18}},"2020-05-28":{"total":{"tested":18}},"2020-05-29":{"total":{"tested":18}},"2020-05-30":{"total":{"tested":18}},"2020-05-31":{"total":{"tested":18}},"2020-06-01":{"total":{"tested":18}},"2020-06-02":{"total":{"tested":18}},"2020-06-03":{"total":{"tested":18}},"2020-06-04":{"total":{"tested":18}},"2020-06-05":{"total":{"tested":18}},"2020-06-06":{"delta":{"confirmed":4},"total":{"confirmed":4,"tested":18}},"2020-06-07":{"total":{"confirmed":4,"tested":18}},"2020-06-08":{"total":{"confirmed":4,"tested":18}},"2020-06-09":{"total":{"confirmed":4,"tested":18}},"2020-06-10":{"total":{"confirmed":4,"tested":18}},"2020-06-11":{"total":{"confirmed":4,"tested":18}},"2020-06-12":{"total":{"confirmed":4,"tested":18}},"2020-06-13":{"total":{"confirmed":4,"tested":18}},"2020-06-14":{"total":{"confirmed":4,"tested":18}},"2020-06-15":{"total":{"confirmed":4,"tested":18}},"2020-06-16":{"total":{"confirmed":4,"tested":18}},"2020-06-17":{"total":{"confirmed":4,"tested":18}},"2020-06-18":{"total":{"confirmed":4,"tested":18}},"2020-06-19":{"total":{"confirmed":4,"tested":18}},"2020-06-20":{"total":{"confirmed":4,"tested":18}},"2020-06-21":{"total":{"confirmed":4,"tested":18}},"2020-06-22":{"total":{"confirmed":4,"tested":18}},"2020-06-23":{"total":{"confirmed":4,"tested":18}},"2020-06-24":{"total":{"confirmed":4,"tested":18}},"2020-06-25":{"total":{"confirmed":4,"tested":18}},"2020-06-26":{"total":{"confirmed":4,"tested":18}},"2020-06-27":{"total":{"confirmed":4,"tested":18}},"2020-06-28":{"total":{"confirmed":4,"tested":18}},"2020-06-29":{"total":{"confirmed":4,"tested":18}},"2020-06-30":{"total":{"confirmed":4,"tested":18}},"2020-07-01":{"total":{"confirmed":4,"tested":18}},"2020-07-02":{"total":{"confirmed":4,"tested":18}},"2020-07-03":{"total":{"confirmed":4,"tested":18}},"2020-07-04":{"total":{"confirmed":4,"tested":18}},"2020-07-05":{"total":{"confirmed":4,"tested":18}},"2020-07-06":{"total":{"confirmed":4,"tested":18}},"2020-07-07":{"total":{"confirmed":4,"tested":18}},"2020-07-08":{"total":{"confirmed":4,"tested":18}},"2020-07-09":{"total":{"confirmed":4,"tested":18}},"2020-07-10":{"total":{"confirmed":4,"tested":18}},"2020-07-11":{"total":{"confirmed":4,"tested":18}},"2020-07-12":{"total":{"confirmed":4,"tested":18}},"2020-07-13":{"total":{"confirmed":4,"tested":18}},"2020-07-14":{"total":{"confirmed":4,"tested":18}},"2020-07-15":{"total":{"confirmed":4,"tested":18}},"2020-07-16":{"total":{"confirmed":4,"tested":18}},"2020-07-17":{"total":{"confirmed":4,"tested":18}},"2020-07-18":{"total":{"confirmed":4,"tested":18}},"2020-07-19":{"total":{"confirmed":4,"tested":18}},"2020-07-20":{"total":{"confirmed":4,"tested":18}},"2020-07-21":{"total":{"confirmed":4,"tested":18}},"2020-07-22":{"total":{"confirmed":4,"tested":18}},"2020-07-23":{"delta":{"recovered":4},"total":{"confirmed":4,"recovered":4,"tested":18}},"2020-07-24":{"total":{"confirmed":4,"recovered":4,"tested":18}},"2020-07-25":{"total":{"confirmed":4,"recovered":4,"tested":18}},"2020-07-26":{"total":{"confirmed":4,"recovered":4,"tested":18}},"2020-07-27":{"total":{"confirmed":4,"recovered":4,"tested":18}},"2020-07-28":{"total":{"confirmed":4,"recovered":4,"tested":18}},"2020-07-29":{"total":{"confirmed":4,"recovered":4,"tested":18}},"2020-07-30":{"total":{"confirmed":4,"recovered":4,"tested":18}},"2020-07-31":{"total":{"confirmed":4,"recovered":4,"tested":18}},"2020-08-01":{"total":{"confirmed":4,"recovered":4,"tested":18}},"2020-08-02":{"total":{"confirmed":4,"recovered":4,"tested":18}},"2020-08-03":{"total":{"confirmed":4,"recovered":4,"tested":18}},"2020-08-04":{"total":{"confirmed":4,"recovered":4,"tested":18}},"2020-08-05":{"total":{"confirmed":4,"recovered":4,"tested":18}},"2020-08-06":{"total":{"confirmed":4,"recovered":4,"tested":18}},"2020-08-07":{"total":{"confirmed":4,"recovered":4,"tested":18}},"2020-08-08":{"total":{"confirmed":4,"recovered":4,"tested":18}},"2020-08-09":{"total":{"confirmed":4,"recovered":4,"tested":18}},"2020-08-10":{"total":{"confirmed":4,"recovered":4,"tested":18}},"2020-08-11":{"total":{"confirmed":4,"recovered":4,"tested":18}},"2020-08-12":{"total":{"confirmed":4,"recovered":4,"tested":18}},"2020-08-13":{"total":{"confirmed":4,"recovered":4,"tested":18}},"2020-08-14":{"total":{"confirmed":4,"recovered":4,"tested":18}},"2020-08-15":{"total":{"confirmed":4,"recovered":4,"tested":18}},"2020-08-16":{"total":{"confirmed":4,"recovered":4,"tested":18}},"2020-08-17":{"total":{"confirmed":4,"recovered":4,"tested":18}},"2020-08-18":{"total":{"confirmed":4,"recovered":4,"tested":18}}}},"Kohima":{"dates":{"2020-05-19":{"delta":{"tested":226},"total":{"tested":226}},"2020-05-20":{"total":{"tested":226}},"2020-05-21":{"total":{"tested":226}},"2020-05-22":{"delta":{"tested":10},"total":{"tested":236}},"2020-05-23":{"delta":{"tested":7},"total":{"tested":243}},"2020-05-24":{"delta":{"tested":16},"total":{"tested":259}},"2020-05-25":{"delta":{"confirmed":1},"total":{"confirmed":1,"tested":259}},"2020-05-26":{"delta":{"confirmed":1,"tested":214},"total":{"confirmed":2,"tested":473}},"2020-05-27":{"delta":{"confirmed":1,"tested":12},"total":{"confirmed":3,"tested":485}},"2020-05-28":{"delta":{"confirmed":2},"total":{"confirmed":5,"tested":485}},"2020-05-29":{"delta":{"confirmed":4},"total":{"confirmed":9,"tested":485}},"2020-05-30":{"delta":{"confirmed":3},"total":{"confirmed":12,"tested":485}},"2020-05-31":{"delta":{"confirmed":4},"total":{"confirmed":16,"tested":485}},"2020-06-01":{"total":{"confirmed":16,"tested":485}},"2020-06-02":{"total":{"confirmed":16,"tested":485}},"2020-06-03":{"total":{"confirmed":16,"tested":485}},"2020-06-04":{"delta":{"confirmed":1},"total":{"confirmed":17,"tested":485}},"2020-06-05":{"total":{"confirmed":17,"tested":485}},"2020-06-06":{"delta":{"confirmed":-12},"total":{"confirmed":5,"tested":485}},"2020-06-07":{"delta":{"confirmed":-2},"total":{"confirmed":3,"tested":485}},"2020-06-08":{"delta":{"confirmed":3},"total":{"confirmed":6,"tested":485}},"2020-06-09":{"delta":{"confirmed":1,"recovered":2},"total":{"confirmed":7,"recovered":2,"tested":485}},"2020-06-10":{"delta":{"confirmed":1,"recovered":8},"total":{"confirmed":8,"recovered":10,"tested":485}},"2020-06-11":{"delta":{"confirmed":2},"total":{"confirmed":10,"recovered":10,"tested":485}},"2020-06-12":{"delta":{"confirmed":2},"total":{"confirmed":12,"recovered":10,"tested":485}},"2020-06-13":{"total":{"confirmed":12,"recovered":10,"tested":485}},"2020-06-14":{"delta":{"confirmed":-5,"recovered":-10},"total":{"confirmed":7,"tested":485}},"2020-06-15":{"total":{"confirmed":7,"tested":485}},"2020-06-16":{"delta":{"confirmed":1},"total":{"confirmed":8,"tested":485}},"2020-06-17":{"total":{"confirmed":8,"tested":485}},"2020-06-18":{"total":{"confirmed":8,"tested":485}},"2020-06-19":{"delta":{"confirmed":1},"total":{"confirmed":9,"tested":485}},"2020-06-20":{"delta":{"confirmed":2},"total":{"confirmed":11,"tested":485}},"2020-06-21":{"delta":{"confirmed":6},"total":{"confirmed":17,"tested":485}},"2020-06-22":{"total":{"confirmed":17,"tested":485}},"2020-06-23":{"delta":{"confirmed":9},"total":{"confirmed":26,"tested":485}},"2020-06-24":{"delta":{"recovered":2},"total":{"confirmed":26,"recovered":2,"tested":485}},"2020-06-25":{"delta":{"confirmed":3,"recovered":2},"total":{"confirmed":29,"recovered":4,"tested":485}},"2020-06-26":{"total":{"confirmed":29,"recovered":4,"tested":485}},"2020-06-27":{"delta":{"confirmed":14},"total":{"confirmed":43,"recovered":4,"tested":485}},"2020-06-28":{"delta":{"confirmed":3},"total":{"confirmed":46,"recovered":4,"tested":485}},"2020-06-29":{"total":{"confirmed":46,"recovered":4,"tested":485}},"2020-06-30":{"total":{"confirmed":46,"recovered":4,"tested":485}},"2020-07-01":{"delta":{"confirmed":2},"total":{"confirmed":48,"recovered":4,"tested":485}},"2020-07-02":{"delta":{"confirmed":1},"total":{"confirmed":49,"recovered":4,"tested":485}},"2020-07-03":{"delta":{"recovered":10},"total":{"confirmed":49,"recovered":14,"tested":485}},"2020-07-04":{"delta":{"confirmed":2},"total":{"confirmed":51,"recovered":14,"tested":485}},"2020-07-05":{"delta":{"confirmed":1},"total":{"confirmed":52,"recovered":14,"tested":485}},"2020-07-06":{"total":{"confirmed":52,"recovered":14,"tested":485}},"2020-07-07":{"delta":{"confirmed":1},"total":{"confirmed":53,"recovered":14,"tested":485}},"2020-07-08":{"delta":{"confirmed":1},"total":{"confirmed":54,"recovered":14,"tested":485}},"2020-07-09":{"total":{"confirmed":54,"recovered":14,"tested":485}},"2020-07-10":{"delta":{"confirmed":20},"total":{"confirmed":74,"recovered":14,"tested":485}},"2020-07-11":{"delta":{"confirmed":7},"total":{"confirmed":81,"recovered":14,"tested":485}},"2020-07-12":{"delta":{"confirmed":1,"recovered":1},"total":{"confirmed":82,"recovered":15,"tested":485}},"2020-07-13":{"delta":{"confirmed":4},"total":{"confirmed":86,"recovered":15,"tested":485}},"2020-07-14":{"delta":{"confirmed":24},"total":{"confirmed":110,"recovered":15,"tested":485}},"2020-07-15":{"delta":{"recovered":1},"total":{"confirmed":110,"recovered":16,"tested":485}},"2020-07-16":{"delta":{"confirmed":2},"total":{"confirmed":112,"recovered":16,"tested":485}},"2020-07-17":{"total":{"confirmed":112,"recovered":16,"tested":485}},"2020-07-18":{"delta":{"confirmed":3},"total":{"confirmed":115,"recovered":16,"tested":485}},"2020-07-19":{"delta":{"confirmed":6},"total":{"confirmed":121,"recovered":16,"tested":485}},"2020-07-20":{"delta":{"confirmed":5},"total":{"confirmed":126,"recovered":16,"tested":485}},"2020-07-21":{"total":{"confirmed":126,"recovered":16,"tested":485}},"2020-07-22":{"delta":{"confirmed":19},"total":{"confirmed":145,"recovered":16,"tested":485}},"2020-07-23":{"delta":{"confirmed":61,"recovered":22},"total":{"confirmed":206,"recovered":38,"tested":485}},"2020-07-24":{"delta":{"confirmed":21,"recovered":7},"total":{"confirmed":227,"recovered":45,"tested":485}},"2020-07-25":{"delta":{"confirmed":7},"total":{"confirmed":234,"recovered":45,"tested":485}},"2020-07-26":{"delta":{"confirmed":28,"recovered":5},"total":{"confirmed":262,"recovered":50,"tested":485}},"2020-07-27":{"delta":{"confirmed":23,"recovered":1},"total":{"confirmed":285,"recovered":51,"tested":485}},"2020-07-28":{"delta":{"confirmed":51,"recovered":3},"total":{"confirmed":336,"recovered":54,"tested":485}},"2020-07-29":{"delta":{"confirmed":19,"recovered":1},"total":{"confirmed":355,"recovered":55,"tested":485}},"2020-07-30":{"delta":{"confirmed":16},"total":{"confirmed":371,"recovered":55,"tested":485}},"2020-07-31":{"delta":{"confirmed":31},"total":{"confirmed":402,"recovered":55,"tested":485}},"2020-08-01":{"delta":{"confirmed":21,"other":1,"recovered":3},"total":{"confirmed":423,"other":1,"recovered":58,"tested":485}},"2020-08-02":{"delta":{"confirmed":17,"recovered":8},"total":{"confirmed":440,"other":1,"recovered":66,"tested":485}},"2020-08-03":{"delta":{"confirmed":22,"recovered":9},"total":{"confirmed":462,"other":1,"recovered":75,"tested":485}},"2020-08-04":{"total":{"confirmed":462,"other":1,"recovered":75,"tested":485}},"2020-08-05":{"delta":{"recovered":-2},"total":{"confirmed":462,"other":1,"recovered":73,"tested":485}},"2020-08-06":{"delta":{"confirmed":27,"recovered":10},"total":{"confirmed":489,"other":1,"recovered":83,"tested":485}},"2020-08-07":{"delta":{"confirmed":3,"deceased":1,"other":-1},"total":{"confirmed":492,"deceased":1,"recovered":83,"tested":485}},"2020-08-08":{"delta":{"confirmed":12,"other":1,"recovered":9},"total":{"confirmed":504,"deceased":1,"other":1,"recovered":92,"tested":485}},"2020-08-09":{"delta":{"confirmed":20,"recovered":1},"total":{"confirmed":524,"deceased":1,"other":1,"recovered":93,"tested":485}},"2020-08-10":{"delta":{"confirmed":104,"recovered":12},"total":{"confirmed":628,"deceased":1,"other":1,"recovered":105,"tested":485}},"2020-08-11":{"delta":{"confirmed":10,"deceased":-1,"other":2,"recovered":11},"total":{"confirmed":638,"other":3,"recovered":116,"tested":485}},"2020-08-12":{"delta":{"confirmed":35,"recovered":5},"total":{"confirmed":673,"other":3,"recovered":121,"tested":485}},"2020-08-13":{"delta":{"confirmed":40,"recovered":27},"total":{"confirmed":713,"other":3,"recovered":148,"tested":485}},"2020-08-14":{"delta":{"confirmed":84,"recovered":14},"total":{"confirmed":797,"other":3,"recovered":162,"tested":485}},"2020-08-15":{"delta":{"confirmed":16,"recovered":68},"total":{"confirmed":813,"other":3,"recovered":230,"tested":485}},"2020-08-16":{"delta":{"confirmed":26,"recovered":2},"total":{"confirmed":839,"other":3,"recovered":232,"tested":485}},"2020-08-17":{"delta":{"confirmed":24,"recovered":30},"total":{"confirmed":863,"other":3,"recovered":262,"tested":485}},"2020-08-18":{"delta":{"confirmed":41,"recovered":36},"total":{"confirmed":904,"other":3,"recovered":298,"tested":485}}}},"Longleng":{"dates":{"2020-06-23":{"delta":{"confirmed":1},"total":{"confirmed":1}},"2020-06-24":{"total":{"confirmed":1}},"2020-06-25":{"total":{"confirmed":1}},"2020-06-26":{"total":{"confirmed":1}},"2020-06-27":{"delta":{"confirmed":1},"total":{"confirmed":2}},"2020-06-28":{"total":{"confirmed":2}},"2020-06-29":{"total":{"confirmed":2}},"2020-06-30":{"total":{"confirmed":2}},"2020-07-01":{"total":{"confirmed":2}},"2020-07-02":{"total":{"confirmed":2}},"2020-07-03":{"total":{"confirmed":2}},"2020-07-04":{"total":{"confirmed":2}},"2020-07-05":{"total":{"confirmed":2}},"2020-07-06":{"total":{"confirmed":2}},"2020-07-07":{"total":{"confirmed":2}},"2020-07-08":{"total":{"confirmed":2}},"2020-07-09":{"total":{"confirmed":2}},"2020-07-10":{"total":{"confirmed":2}},"2020-07-11":{"total":{"confirmed":2}},"2020-07-12":{"total":{"confirmed":2}},"2020-07-13":{"total":{"confirmed":2}},"2020-07-14":{"delta":{"confirmed":2},"total":{"confirmed":4}},"2020-07-15":{"total":{"confirmed":4}},"2020-07-16":{"total":{"confirmed":4}},"2020-07-17":{"total":{"confirmed":4}},"2020-07-18":{"total":{"confirmed":4}},"2020-07-19":{"delta":{"confirmed":1},"total":{"confirmed":5}},"2020-07-20":{"total":{"confirmed":5}},"2020-07-21":{"total":{"confirmed":5}},"2020-07-22":{"total":{"confirmed":5}},"2020-07-23":{"delta":{"recovered":2},"total":{"confirmed":5,"recovered":2}},"2020-07-24":{"total":{"confirmed":5,"recovered":2}},"2020-07-25":{"total":{"confirmed":5,"recovered":2}},"2020-07-26":{"delta":{"recovered":2},"total":{"confirmed":5,"recovered":4}},"2020-07-27":{"total":{"confirmed":5,"recovered":4}},"2020-07-28":{"total":{"confirmed":5,"recovered":4}},"2020-07-29":{"total":{"confirmed":5,"recovered":4}},"2020-07-30":{"delta":{"recovered":1},"total":{"confirmed":5,"recovered":5}},"2020-07-31":{"total":{"confirmed":5,"recovered":5}},"2020-08-01":{"total":{"confirmed":5,"recovered":5}},"2020-08-02":{"total":{"confirmed":5,"recovered":5}},"2020-08-03":{"total":{"confirmed":5,"recovered":5}},"2020-08-04":{"total":{"confirmed":5,"recovered":5}},"2020-08-05":{"total":{"confirmed":5,"recovered":5}},"2020-08-06":{"total":{"confirmed":5,"recovered":5}},"2020-08-07":{"total":{"confirmed":5,"recovered":5}},"2020-08-08":{"total":{"confirmed":5,"recovered":5}},"2020-08-09":{"total":{"confirmed":5,"recovered":5}},"2020-08-10":{"total":{"confirmed":5,"recovered":5}},"2020-08-11":{"total":{"confirmed":5,"recovered":5}},"2020-08-12":{"total":{"confirmed":5,"recovered":5}},"2020-08-13":{"total":{"confirmed":5,"recovered":5}},"2020-08-14":{"total":{"confirmed":5,"recovered":5}},"2020-08-15":{"total":{"confirmed":5,"recovered":5}},"2020-08-16":{"total":{"confirmed":5,"recovered":5}},"2020-08-17":{"total":{"confirmed":5,"recovered":5}},"2020-08-18":{"total":{"confirmed":5,"recovered":5}}}},"Mokokchung":{"dates":{"2020-05-19":{"delta":{"tested":2},"total":{"tested":2}},"2020-05-20":{"total":{"tested":2}},"2020-05-21":{"total":{"tested":2}},"2020-05-22":{"delta":{"tested":2},"total":{"tested":4}},"2020-05-23":{"total":{"tested":4}},"2020-05-24":{"delta":{"tested":1},"total":{"tested":5}},"2020-05-25":{"total":{"tested":5}},"2020-05-26":{"delta":{"tested":1},"total":{"tested":6}},"2020-05-27":{"delta":{"tested":57},"total":{"tested":63}},"2020-05-28":{"total":{"tested":63}},"2020-05-29":{"total":{"tested":63}},"2020-05-30":{"total":{"tested":63}},"2020-05-31":{"total":{"tested":63}},"2020-06-01":{"total":{"tested":63}},"2020-06-02":{"total":{"tested":63}},"2020-06-03":{"total":{"tested":63}},"2020-06-04":{"total":{"tested":63}},"2020-06-05":{"total":{"tested":63}},"2020-06-06":{"total":{"tested":63}},"2020-06-07":{"total":{"tested":63}},"2020-06-08":{"total":{"tested":63}},"2020-06-09":{"total":{"tested":63}},"2020-06-10":{"total":{"tested":63}},"2020-06-11":{"total":{"tested":63}},"2020-06-12":{"total":{"tested":63}},"2020-06-13":{"total":{"tested":63}},"2020-06-14":{"total":{"tested":63}},"2020-06-15":{"total":{"tested":63}},"2020-06-16":{"total":{"tested":63}},"2020-06-17":{"total":{"tested":63}},"2020-06-18":{"total":{"tested":63}},"2020-06-19":{"total":{"tested":63}},"2020-06-20":{"total":{"tested":63}},"2020-06-21":{"total":{"tested":63}},"2020-06-22":{"total":{"tested":63}},"2020-06-23":{"total":{"tested":63}},"2020-06-24":{"total":{"tested":63}},"2020-06-25":{"total":{"tested":63}},"2020-06-26":{"total":{"tested":63}},"2020-06-27":{"total":{"tested":63}},"2020-06-28":{"total":{"tested":63}},"2020-06-29":{"total":{"tested":63}},"2020-06-30":{"delta":{"confirmed":1},"total":{"confirmed":1,"tested":63}},"2020-07-01":{"total":{"confirmed":1,"tested":63}},"2020-07-02":{"total":{"confirmed":1,"tested":63}},"2020-07-03":{"total":{"confirmed":1,"tested":63}},"2020-07-04":{"total":{"confirmed":1,"tested":63}},"2020-07-05":{"delta":{"confirmed":1},"total":{"confirmed":2,"tested":63}},"2020-07-06":{"total":{"confirmed":2,"tested":63}},"2020-07-07":{"total":{"confirmed":2,"tested":63}},"2020-07-08":{"delta":{"confirmed":1},"total":{"confirmed":3,"tested":63}},"2020-07-09":{"total":{"confirmed":3,"tested":63}},"2020-07-10":{"total":{"confirmed":3,"tested":63}},"2020-07-11":{"delta":{"confirmed":1},"total":{"confirmed":4,"tested":63}},"2020-07-12":{"total":{"confirmed":4,"tested":63}},"2020-07-13":{"total":{"confirmed":4,"tested":63}},"2020-07-14":{"delta":{"confirmed":1},"total":{"confirmed":5,"tested":63}},"2020-07-15":{"total":{"confirmed":5,"tested":63}},"2020-07-16":{"total":{"confirmed":5,"tested":63}},"2020-07-17":{"total":{"confirmed":5,"tested":63}},"2020-07-18":{"total":{"confirmed":5,"tested":63}},"2020-07-19":{"delta":{"confirmed":2},"total":{"confirmed":7,"tested":63}},"2020-07-20":{"total":{"confirmed":7,"tested":63}},"2020-07-21":{"total":{"confirmed":7,"tested":63}},"2020-07-22":{"delta":{"confirmed":2},"total":{"confirmed":9,"tested":63}},"2020-07-23":{"delta":{"recovered":4},"total":{"confirmed":9,"recovered":4,"tested":63}},"2020-07-24":{"total":{"confirmed":9,"recovered":4,"tested":63}},"2020-07-25":{"delta":{"confirmed":4},"total":{"confirmed":13,"recovered":4,"tested":63}},"2020-07-26":{"total":{"confirmed":13,"recovered":4,"tested":63}},"2020-07-27":{"delta":{"recovered":1},"total":{"confirmed":13,"recovered":5,"tested":63}},"2020-07-28":{"total":{"confirmed":13,"recovered":5,"tested":63}},"2020-07-29":{"total":{"confirmed":13,"recovered":5,"tested":63}},"2020-07-30":{"delta":{"confirmed":5},"total":{"confirmed":18,"recovered":5,"tested":63}},"2020-07-31":{"delta":{"recovered":2},"total":{"confirmed":18,"recovered":7,"tested":63}},"2020-08-01":{"total":{"confirmed":18,"recovered":7,"tested":63}},"2020-08-02":{"total":{"confirmed":18,"recovered":7,"tested":63}},"2020-08-03":{"total":{"confirmed":18,"recovered":7,"tested":63}},"2020-08-04":{"total":{"confirmed":18,"recovered":7,"tested":63}},"2020-08-05":{"delta":{"recovered":2},"total":{"confirmed":18,"recovered":9,"tested":63}},"2020-08-06":{"delta":{"recovered":2},"total":{"confirmed":18,"recovered":11,"tested":63}},"2020-08-07":{"total":{"confirmed":18,"recovered":11,"tested":63}},"2020-08-08":{"delta":{"recovered":2},"total":{"confirmed":18,"recovered":13,"tested":63}},"2020-08-09":{"total":{"confirmed":18,"recovered":13,"tested":63}},"2020-08-10":{"total":{"confirmed":18,"recovered":13,"tested":63}},"2020-08-11":{"total":{"confirmed":18,"recovered":13,"tested":63}},"2020-08-12":{"delta":{"recovered":-1},"total":{"confirmed":18,"recovered":12,"tested":63}},"2020-08-13":{"total":{"confirmed":18,"recovered":12,"tested":63}},"2020-08-14":{"delta":{"recovered":3},"total":{"confirmed":18,"recovered":15,"tested":63}},"2020-08-15":{"delta":{"recovered":1},"total":{"confirmed":18,"recovered":16,"tested":63}},"2020-08-16":{"delta":{"recovered":1},"total":{"confirmed":18,"recovered":17,"tested":63}},"2020-08-17":{"delta":{"confirmed":1},"total":{"confirmed":19,"recovered":17,"tested":63}},"2020-08-18":{"total":{"confirmed":19,"recovered":17,"tested":63}}}},"Mon":{"dates":{"2020-05-19":{"delta":{"tested":8},"total":{"tested":8}},"2020-05-20":{"total":{"tested":8}},"2020-05-21":{"total":{"tested":8}},"2020-05-22":{"delta":{"tested":25},"total":{"tested":33}},"2020-05-23":{"delta":{"tested":3},"total":{"tested":36}},"2020-05-24":{"total":{"tested":36}},"2020-05-25":{"total":{"tested":36}},"2020-05-26":{"delta":{"tested":8},"total":{"tested":44}},"2020-05-27":{"delta":{"tested":1},"total":{"tested":45}},"2020-05-28":{"total":{"tested":45}},"2020-05-29":{"total":{"tested":45}},"2020-05-30":{"total":{"tested":45}},"2020-05-31":{"total":{"tested":45}},"2020-06-01":{"total":{"tested":45}},"2020-06-02":{"total":{"tested":45}},"2020-06-03":{"total":{"tested":45}},"2020-06-04":{"total":{"tested":45}},"2020-06-05":{"total":{"tested":45}},"2020-06-06":{"delta":{"confirmed":23},"total":{"confirmed":23,"tested":45}},"2020-06-07":{"total":{"confirmed":23,"tested":45}},"2020-06-08":{"total":{"confirmed":23,"tested":45}},"2020-06-09":{"total":{"confirmed":23,"tested":45}},"2020-06-10":{"total":{"confirmed":23,"tested":45}},"2020-06-11":{"total":{"confirmed":23,"tested":45}},"2020-06-12":{"total":{"confirmed":23,"tested":45}},"2020-06-13":{"total":{"confirmed":23,"tested":45}},"2020-06-14":{"delta":{"confirmed":10},"total":{"confirmed":33,"tested":45}},"2020-06-15":{"total":{"confirmed":33,"tested":45}},"2020-06-16":{"total":{"confirmed":33,"tested":45}},"2020-06-17":{"delta":{"confirmed":12},"total":{"confirmed":45,"tested":45}},"2020-06-18":{"total":{"confirmed":45,"tested":45}},"2020-06-19":{"delta":{"confirmed":2},"total":{"confirmed":47,"tested":45}},"2020-06-20":{"delta":{"confirmed":1},"total":{"confirmed":48,"tested":45}},"2020-06-21":{"total":{"confirmed":48,"tested":45}},"2020-06-22":{"total":{"confirmed":48,"tested":45}},"2020-06-23":{"total":{"confirmed":48,"tested":45}},"2020-06-24":{"total":{"confirmed":48,"tested":45}},"2020-06-25":{"total":{"confirmed":48,"tested":45}},"2020-06-26":{"total":{"confirmed":48,"tested":45}},"2020-06-27":{"delta":{"confirmed":12},"total":{"confirmed":60,"tested":45}},"2020-06-28":{"delta":{"confirmed":3},"total":{"confirmed":63,"tested":45}},"2020-06-29":{"total":{"confirmed":63,"tested":45}},"2020-06-30":{"total":{"confirmed":63,"tested":45}},"2020-07-01":{"total":{"confirmed":63,"tested":45}},"2020-07-02":{"total":{"confirmed":63,"tested":45}},"2020-07-03":{"delta":{"confirmed":3},"total":{"confirmed":66,"tested":45}},"2020-07-04":{"total":{"confirmed":66,"tested":45}},"2020-07-05":{"delta":{"confirmed":1},"total":{"confirmed":67,"tested":45}},"2020-07-06":{"delta":{"confirmed":20},"total":{"confirmed":87,"tested":45}},"2020-07-07":{"delta":{"confirmed":10},"total":{"confirmed":97,"tested":45}},"2020-07-08":{"delta":{"confirmed":1},"total":{"confirmed":98,"tested":45}},"2020-07-09":{"total":{"confirmed":98,"tested":45}},"2020-07-10":{"total":{"confirmed":98,"tested":45}},"2020-07-11":{"delta":{"confirmed":3},"total":{"confirmed":101,"tested":45}},"2020-07-12":{"total":{"confirmed":101,"tested":45}},"2020-07-13":{"delta":{"confirmed":7},"total":{"confirmed":108,"tested":45}},"2020-07-14":{"total":{"confirmed":108,"tested":45}},"2020-07-15":{"total":{"confirmed":108,"tested":45}},"2020-07-16":{"total":{"confirmed":108,"tested":45}},"2020-07-17":{"total":{"confirmed":108,"tested":45}},"2020-07-18":{"total":{"confirmed":108,"tested":45}},"2020-07-19":{"total":{"confirmed":108,"tested":45}},"2020-07-20":{"delta":{"confirmed":12},"total":{"confirmed":120,"tested":45}},"2020-07-21":{"delta":{"confirmed":2},"total":{"confirmed":122,"tested":45}},"2020-07-22":{"delta":{"confirmed":2},"total":{"confirmed":124,"tested":45}},"2020-07-23":{"delta":{"recovered":33},"total":{"confirmed":124,"recovered":33,"tested":45}},"2020-07-24":{"total":{"confirmed":124,"recovered":33,"tested":45}},"2020-07-25":{"delta":{"confirmed":20},"total":{"confirmed":144,"recovered":33,"tested":45}},"2020-07-26":{"delta":{"confirmed":13},"total":{"confirmed":157,"recovered":33,"tested":45}},"2020-07-27":{"delta":{"confirmed":8},"total":{"confirmed":165,"recovered":33,"tested":45}},"2020-07-28":{"delta":{"confirmed":3},"total":{"confirmed":168,"recovered":33,"tested":45}},"2020-07-29":{"delta":{"confirmed":5,"recovered":2},"total":{"confirmed":173,"recovered":35,"tested":45}},"2020-07-30":{"delta":{"recovered":29},"total":{"confirmed":173,"recovered":64,"tested":45}},"2020-07-31":{"total":{"confirmed":173,"recovered":64,"tested":45}},"2020-08-01":{"total":{"confirmed":173,"recovered":64,"tested":45}},"2020-08-02":{"delta":{"confirmed":1},"total":{"confirmed":174,"recovered":64,"tested":45}},"2020-08-03":{"total":{"confirmed":174,"recovered":64,"tested":45}},"2020-08-04":{"delta":{"confirmed":89},"total":{"confirmed":263,"recovered":64,"tested":45}},"2020-08-05":{"delta":{"confirmed":5,"recovered":5},"total":{"confirmed":268,"recovered":69,"tested":45}},"2020-08-06":{"delta":{"confirmed":-5,"recovered":30},"total":{"confirmed":263,"recovered":99,"tested":45}},"2020-08-07":{"total":{"confirmed":263,"recovered":99,"tested":45}},"2020-08-08":{"total":{"confirmed":263,"recovered":99,"tested":45}},"2020-08-09":{"delta":{"confirmed":2},"total":{"confirmed":265,"recovered":99,"tested":45}},"2020-08-10":{"delta":{"confirmed":18,"recovered":23},"total":{"confirmed":283,"recovered":122,"tested":45}},"2020-08-11":{"delta":{"other":2},"total":{"confirmed":283,"other":2,"recovered":122,"tested":45}},"2020-08-12":{"delta":{"recovered":48},"total":{"confirmed":283,"other":2,"recovered":170,"tested":45}},"2020-08-13":{"delta":{"confirmed":4},"total":{"confirmed":287,"other":2,"recovered":170,"tested":45}},"2020-08-14":{"delta":{"confirmed":1},"total":{"confirmed":288,"other":2,"recovered":170,"tested":45}},"2020-08-15":{"total":{"confirmed":288,"other":2,"recovered":170,"tested":45}},"2020-08-16":{"delta":{"recovered":41},"total":{"confirmed":288,"other":2,"recovered":211,"tested":45}},"2020-08-17":{"delta":{"recovered":4},"total":{"confirmed":288,"other":2,"recovered":215,"tested":45}},"2020-08-18":{"delta":{"confirmed":1},"total":{"confirmed":289,"other":2,"recovered":215,"tested":45}}}},"Others":{"dates":{"2020-06-14":{"delta":{"confirmed":2},"total":{"confirmed":2}},"2020-06-15":{"total":{"confirmed":2}},"2020-06-16":{"total":{"confirmed":2}},"2020-06-17":{"total":{"confirmed":2}},"2020-06-18":{"total":{"confirmed":2}},"2020-06-19":{"delta":{"confirmed":1},"total":{"confirmed":3}},"2020-06-20":{"total":{"confirmed":3}},"2020-06-21":{"total":{"confirmed":3}},"2020-06-22":{"total":{"confirmed":3}},"2020-06-23":{"delta":{"confirmed":3},"total":{"confirmed":6}},"2020-06-24":{"delta":{"confirmed":12},"total":{"confirmed":18}},"2020-06-25":{"delta":{"confirmed":4},"total":{"confirmed":22}},"2020-06-26":{"total":{"confirmed":22}},"2020-06-27":{"total":{"confirmed":22}},"2020-06-28":{"total":{"confirmed":22}},"2020-06-29":{"delta":{"confirmed":18},"total":{"confirmed":40}},"2020-06-30":{"delta":{"confirmed":6},"total":{"confirmed":46}},"2020-07-01":{"total":{"confirmed":46}},"2020-07-02":{"total":{"confirmed":46}},"2020-07-03":{"total":{"confirmed":46}},"2020-07-04":{"total":{"confirmed":46}},"2020-07-05":{"total":{"confirmed":46}},"2020-07-06":{"total":{"confirmed":46}},"2020-07-07":{"total":{"confirmed":46}},"2020-07-08":{"total":{"confirmed":46}},"2020-07-09":{"total":{"confirmed":46}},"2020-07-10":{"total":{"confirmed":46}},"2020-07-11":{"total":{"confirmed":46}},"2020-07-12":{"total":{"confirmed":46}},"2020-07-13":{"total":{"confirmed":46}},"2020-07-14":{"total":{"confirmed":46}},"2020-07-15":{"total":{"confirmed":46}},"2020-07-16":{"total":{"confirmed":46}},"2020-07-17":{"total":{"confirmed":46}},"2020-07-18":{"total":{"confirmed":46}},"2020-07-19":{"total":{"confirmed":46}},"2020-07-20":{"total":{"confirmed":46}},"2020-07-21":{"total":{"confirmed":46}},"2020-07-22":{"total":{"confirmed":46}},"2020-07-23":{"delta":{"recovered":46},"total":{"confirmed":46,"recovered":46}},"2020-07-24":{"total":{"confirmed":46,"recovered":46}},"2020-07-25":{"total":{"confirmed":46,"recovered":46}},"2020-07-26":{"total":{"confirmed":46,"recovered":46}},"2020-07-27":{"total":{"confirmed":46,"recovered":46}},"2020-07-28":{"total":{"confirmed":46,"recovered":46}},"2020-07-29":{"total":{"confirmed":46,"recovered":46}},"2020-07-30":{"total":{"confirmed":46,"recovered":46}},"2020-07-31":{"total":{"confirmed":46,"recovered":46}},"2020-08-01":{"total":{"confirmed":46,"recovered":46}},"2020-08-02":{"total":{"confirmed":46,"recovered":46}},"2020-08-03":{"total":{"confirmed":46,"recovered":46}},"2020-08-04":{"total":{"confirmed":46,"recovered":46}},"2020-08-05":{"total":{"confirmed":46,"recovered":46}},"2020-08-06":{"total":{"confirmed":46,"recovered":46}},"2020-08-07":{"total":{"confirmed":46,"recovered":46}},"2020-08-08":{"total":{"confirmed":46,"recovered":46}},"2020-08-09":{"total":{"confirmed":46,"recovered":46}},"2020-08-10":{"total":{"confirmed":46,"recovered":46}},"2020-08-11":{"total":{"confirmed":46,"recovered":46}},"2020-08-12":{"total":{"confirmed":46,"recovered":46}},"2020-08-13":{"total":{"confirmed":46,"recovered":46}},"2020-08-14":{"total":{"confirmed":46,"recovered":46}},"2020-08-15":{"total":{"confirmed":46,"recovered":46}},"2020-08-16":{"total":{"confirmed":46,"recovered":46}},"2020-08-17":{"total":{"confirmed":46,"recovered":46}},"2020-08-18":{"total":{"confirmed":46,"recovered":46}}}},"Peren":{"dates":{"2020-05-19":{"delta":{"tested":11},"total":{"tested":11}},"2020-05-20":{"total":{"tested":11}},"2020-05-21":{"total":{"tested":11}},"2020-05-22":{"total":{"tested":11}},"2020-05-23":{"total":{"tested":11}},"2020-05-24":{"total":{"tested":11}},"2020-05-25":{"total":{"tested":11}},"2020-05-26":{"total":{"tested":11}},"2020-05-27":{"total":{"tested":11}},"2020-05-28":{"total":{"tested":11}},"2020-05-29":{"total":{"tested":11}},"2020-05-30":{"total":{"tested":11}},"2020-05-31":{"total":{"tested":11}},"2020-06-01":{"total":{"tested":11}},"2020-06-02":{"total":{"tested":11}},"2020-06-03":{"total":{"tested":11}},"2020-06-04":{"delta":{"confirmed":1},"total":{"confirmed":1,"tested":11}},"2020-06-05":{"total":{"confirmed":1,"tested":11}},"2020-06-06":{"delta":{"confirmed":52},"total":{"confirmed":53,"tested":11}},"2020-06-07":{"total":{"confirmed":53,"tested":11}},"2020-06-08":{"delta":{"confirmed":9},"total":{"confirmed":62,"tested":11}},"2020-06-09":{"total":{"confirmed":62,"tested":11}},"2020-06-10":{"total":{"confirmed":62,"tested":11}},"2020-06-11":{"total":{"confirmed":62,"tested":11}},"2020-06-12":{"delta":{"confirmed":1},"total":{"confirmed":63,"tested":11}},"2020-06-13":{"total":{"confirmed":63,"tested":11}},"2020-06-14":{"delta":{"confirmed":17},"total":{"confirmed":80,"tested":11}},"2020-06-15":{"delta":{"confirmed":4},"total":{"confirmed":84,"tested":11}},"2020-06-16":{"total":{"confirmed":84,"tested":11}},"2020-06-17":{"total":{"confirmed":84,"tested":11}},"2020-06-18":{"delta":{"recovered":2},"total":{"confirmed":84,"recovered":2,"tested":11}},"2020-06-19":{"total":{"confirmed":84,"recovered":2,"tested":11}},"2020-06-20":{"total":{"confirmed":84,"recovered":2,"tested":11}},"2020-06-21":{"total":{"confirmed":84,"recovered":2,"tested":11}},"2020-06-22":{"delta":{"confirmed":65},"total":{"confirmed":149,"recovered":2,"tested":11}},"2020-06-23":{"delta":{"confirmed":12},"total":{"confirmed":161,"recovered":2,"tested":11}},"2020-06-24":{"total":{"confirmed":161,"recovered":2,"tested":11}},"2020-06-25":{"delta":{"recovered":2},"total":{"confirmed":161,"recovered":4,"tested":11}},"2020-06-26":{"delta":{"recovered":2},"total":{"confirmed":161,"recovered":6,"tested":11}},"2020-06-27":{"delta":{"confirmed":1},"total":{"confirmed":162,"recovered":6,"tested":11}},"2020-06-28":{"delta":{"confirmed":2},"total":{"confirmed":164,"recovered":6,"tested":11}},"2020-06-29":{"delta":{"confirmed":1},"total":{"confirmed":165,"recovered":6,"tested":11}},"2020-06-30":{"total":{"confirmed":165,"recovered":6,"tested":11}},"2020-07-01":{"delta":{"confirmed":31},"total":{"confirmed":196,"recovered":6,"tested":11}},"2020-07-02":{"delta":{"confirmed":32},"total":{"confirmed":228,"recovered":6,"tested":11}},"2020-07-03":{"delta":{"confirmed":1,"recovered":10},"total":{"confirmed":229,"recovered":16,"tested":11}},"2020-07-04":{"delta":{"confirmed":21},"total":{"confirmed":250,"recovered":16,"tested":11}},"2020-07-05":{"delta":{"confirmed":10},"total":{"confirmed":260,"recovered":16,"tested":11}},"2020-07-06":{"total":{"confirmed":260,"recovered":16,"tested":11}},"2020-07-07":{"total":{"confirmed":260,"recovered":16,"tested":11}},"2020-07-08":{"total":{"confirmed":260,"recovered":16,"tested":11}},"2020-07-09":{"delta":{"confirmed":13},"total":{"confirmed":273,"recovered":16,"tested":11}},"2020-07-10":{"delta":{"confirmed":19},"total":{"confirmed":292,"recovered":16,"tested":11}},"2020-07-11":{"total":{"confirmed":292,"recovered":16,"tested":11}},"2020-07-12":{"delta":{"recovered":5},"total":{"confirmed":292,"recovered":21,"tested":11}},"2020-07-13":{"total":{"confirmed":292,"recovered":21,"tested":11}},"2020-07-14":{"delta":{"confirmed":20},"total":{"confirmed":312,"recovered":21,"tested":11}},"2020-07-15":{"total":{"confirmed":312,"recovered":21,"tested":11}},"2020-07-16":{"delta":{"recovered":43},"total":{"confirmed":312,"recovered":64,"tested":11}},"2020-07-17":{"delta":{"confirmed":1,"recovered":14},"total":{"confirmed":313,"recovered":78,"tested":11}},"2020-07-18":{"delta":{"confirmed":11},"total":{"confirmed":324,"recovered":78,"tested":11}},"2020-07-19":{"total":{"confirmed":324,"recovered":78,"tested":11}},"2020-07-20":{"total":{"confirmed":324,"recovered":78,"tested":11}},"2020-07-21":{"delta":{"confirmed":1},"total":{"confirmed":325,"recovered":78,"tested":11}},"2020-07-22":{"delta":{"confirmed":1},"total":{"confirmed":326,"recovered":78,"tested":11}},"2020-07-23":{"delta":{"confirmed":2,"recovered":192},"total":{"confirmed":328,"recovered":270,"tested":11}},"2020-07-24":{"delta":{"confirmed":2},"total":{"confirmed":330,"recovered":270,"tested":11}},"2020-07-25":{"delta":{"recovered":3},"total":{"confirmed":330,"recovered":273,"tested":11}},"2020-07-26":{"total":{"confirmed":330,"recovered":273,"tested":11}},"2020-07-27":{"delta":{"confirmed":1,"recovered":13},"total":{"confirmed":331,"recovered":286,"tested":11}},"2020-07-28":{"delta":{"recovered":5},"total":{"confirmed":331,"recovered":291,"tested":11}},"2020-07-29":{"delta":{"recovered":10},"total":{"confirmed":331,"recovered":301,"tested":11}},"2020-07-30":{"total":{"confirmed":331,"recovered":301,"tested":11}},"2020-07-31":{"delta":{"recovered":8},"total":{"confirmed":331,"recovered":309,"tested":11}},"2020-08-01":{"delta":{"recovered":1},"total":{"confirmed":331,"recovered":310,"tested":11}},"2020-08-02":{"total":{"confirmed":331,"recovered":310,"tested":11}},"2020-08-03":{"total":{"confirmed":331,"recovered":310,"tested":11}},"2020-08-04":{"total":{"confirmed":331,"recovered":310,"tested":11}},"2020-08-05":{"delta":{"recovered":18},"total":{"confirmed":331,"recovered":328,"tested":11}},"2020-08-06":{"total":{"confirmed":331,"recovered":328,"tested":11}},"2020-08-07":{"total":{"confirmed":331,"recovered":328,"tested":11}},"2020-08-08":{"total":{"confirmed":331,"recovered":328,"tested":11}},"2020-08-09":{"delta":{"confirmed":8},"total":{"confirmed":339,"recovered":328,"tested":11}},"2020-08-10":{"delta":{"confirmed":4},"total":{"confirmed":343,"recovered":328,"tested":11}},"2020-08-11":{"total":{"confirmed":343,"recovered":328,"tested":11}},"2020-08-12":{"total":{"confirmed":343,"recovered":328,"tested":11}},"2020-08-13":{"total":{"confirmed":343,"recovered":328,"tested":11}},"2020-08-14":{"delta":{"recovered":1},"total":{"confirmed":343,"recovered":329,"tested":11}},"2020-08-15":{"total":{"confirmed":343,"recovered":329,"tested":11}},"2020-08-16":{"total":{"confirmed":343,"recovered":329,"tested":11}},"2020-08-17":{"total":{"confirmed":343,"recovered":329,"tested":11}},"2020-08-18":{"total":{"confirmed":343,"recovered":329,"tested":11}}}},"Phek":{"dates":{"2020-05-19":{"delta":{"tested":1},"total":{"tested":1}},"2020-05-20":{"total":{"tested":1}},"2020-05-21":{"total":{"tested":1}},"2020-05-22":{"total":{"tested":1}},"2020-05-23":{"total":{"tested":1}},"2020-05-24":{"total":{"tested":1}},"2020-05-25":{"total":{"tested":1}},"2020-05-26":{"delta":{"tested":27},"total":{"tested":28}},"2020-05-27":{"total":{"tested":28}},"2020-05-28":{"total":{"tested":28}},"2020-05-29":{"total":{"tested":28}},"2020-05-30":{"total":{"tested":28}},"2020-05-31":{"total":{"tested":28}},"2020-06-01":{"total":{"tested":28}},"2020-06-02":{"total":{"tested":28}},"2020-06-03":{"total":{"tested":28}},"2020-06-04":{"total":{"tested":28}},"2020-06-05":{"total":{"tested":28}},"2020-06-06":{"delta":{"confirmed":1},"total":{"confirmed":1,"tested":28}},"2020-06-07":{"total":{"confirmed":1,"tested":28}},"2020-06-08":{"total":{"confirmed":1,"tested":28}},"2020-06-09":{"total":{"confirmed":1,"tested":28}},"2020-06-10":{"total":{"confirmed":1,"tested":28}},"2020-06-11":{"total":{"confirmed":1,"tested":28}},"2020-06-12":{"total":{"confirmed":1,"tested":28}},"2020-06-13":{"total":{"confirmed":1,"tested":28}},"2020-06-14":{"total":{"confirmed":1,"tested":28}},"2020-06-15":{"total":{"confirmed":1,"tested":28}},"2020-06-16":{"total":{"confirmed":1,"tested":28}},"2020-06-17":{"total":{"confirmed":1,"tested":28}},"2020-06-18":{"total":{"confirmed":1,"tested":28}},"2020-06-19":{"total":{"confirmed":1,"tested":28}},"2020-06-20":{"total":{"confirmed":1,"tested":28}},"2020-06-21":{"delta":{"confirmed":1},"total":{"confirmed":2,"tested":28}},"2020-06-22":{"total":{"confirmed":2,"tested":28}},"2020-06-23":{"total":{"confirmed":2,"tested":28}},"2020-06-24":{"total":{"confirmed":2,"tested":28}},"2020-06-25":{"total":{"confirmed":2,"tested":28}},"2020-06-26":{"total":{"confirmed":2,"tested":28}},"2020-06-27":{"total":{"confirmed":2,"tested":28}},"2020-06-28":{"total":{"confirmed":2,"tested":28}},"2020-06-29":{"total":{"confirmed":2,"tested":28}},"2020-06-30":{"total":{"confirmed":2,"tested":28}},"2020-07-01":{"delta":{"confirmed":8},"total":{"confirmed":10,"tested":28}},"2020-07-02":{"total":{"confirmed":10,"tested":28}},"2020-07-03":{"delta":{"recovered":1},"total":{"confirmed":10,"recovered":1,"tested":28}},"2020-07-04":{"total":{"confirmed":10,"recovered":1,"tested":28}},"2020-07-05":{"total":{"confirmed":10,"recovered":1,"tested":28}},"2020-07-06":{"total":{"confirmed":10,"recovered":1,"tested":28}},"2020-07-07":{"total":{"confirmed":10,"recovered":1,"tested":28}},"2020-07-08":{"total":{"confirmed":10,"recovered":1,"tested":28}},"2020-07-09":{"delta":{"confirmed":3},"total":{"confirmed":13,"recovered":1,"tested":28}},"2020-07-10":{"delta":{"confirmed":1},"total":{"confirmed":14,"recovered":1,"tested":28}},"2020-07-11":{"total":{"confirmed":14,"recovered":1,"tested":28}},"2020-07-12":{"delta":{"confirmed":4,"recovered":8},"total":{"confirmed":18,"recovered":9,"tested":28}},"2020-07-13":{"total":{"confirmed":18,"recovered":9,"tested":28}},"2020-07-14":{"total":{"confirmed":18,"recovered":9,"tested":28}},"2020-07-15":{"total":{"confirmed":18,"recovered":9,"tested":28}},"2020-07-16":{"total":{"confirmed":18,"recovered":9,"tested":28}},"2020-07-17":{"total":{"confirmed":18,"recovered":9,"tested":28}},"2020-07-18":{"total":{"confirmed":18,"recovered":9,"tested":28}},"2020-07-19":{"total":{"confirmed":18,"recovered":9,"tested":28}},"2020-07-20":{"total":{"confirmed":18,"recovered":9,"tested":28}},"2020-07-21":{"total":{"confirmed":18,"recovered":9,"tested":28}},"2020-07-22":{"total":{"confirmed":18,"recovered":9,"tested":28}},"2020-07-23":{"delta":{"confirmed":1,"recovered":1},"total":{"confirmed":19,"recovered":10,"tested":28}},"2020-07-24":{"total":{"confirmed":19,"recovered":10,"tested":28}},"2020-07-25":{"delta":{"recovered":5},"total":{"confirmed":19,"recovered":15,"tested":28}},"2020-07-26":{"total":{"confirmed":19,"recovered":15,"tested":28}},"2020-07-27":{"total":{"confirmed":19,"recovered":15,"tested":28}},"2020-07-28":{"delta":{"confirmed":10},"total":{"confirmed":29,"recovered":15,"tested":28}},"2020-07-29":{"delta":{"recovered":1},"total":{"confirmed":29,"recovered":16,"tested":28}},"2020-07-30":{"total":{"confirmed":29,"recovered":16,"tested":28}},"2020-07-31":{"total":{"confirmed":29,"recovered":16,"tested":28}},"2020-08-01":{"total":{"confirmed":29,"recovered":16,"tested":28}},"2020-08-02":{"delta":{"confirmed":1},"total":{"confirmed":30,"recovered":16,"tested":28}},"2020-08-03":{"total":{"confirmed":30,"recovered":16,"tested":28}},"2020-08-04":{"delta":{"recovered":2},"total":{"confirmed":30,"recovered":18,"tested":28}},"2020-08-05":{"total":{"confirmed":30,"recovered":18,"tested":28}},"2020-08-06":{"delta":{"confirmed":2},"total":{"confirmed":32,"recovered":18,"tested":28}},"2020-08-07":{"total":{"confirmed":32,"recovered":18,"tested":28}},"2020-08-08":{"delta":{"recovered":5},"total":{"confirmed":32,"recovered":23,"tested":28}},"2020-08-09":{"delta":{"recovered":6},"total":{"confirmed":32,"recovered":29,"tested":28}},"2020-08-10":{"total":{"confirmed":32,"recovered":29,"tested":28}},"2020-08-11":{"total":{"confirmed":32,"recovered":29,"tested":28}},"2020-08-12":{"total":{"confirmed":32,"recovered":29,"tested":28}},"2020-08-13":{"total":{"confirmed":32,"recovered":29,"tested":28}},"2020-08-14":{"delta":{"recovered":1},"total":{"confirmed":32,"recovered":30,"tested":28}},"2020-08-15":{"total":{"confirmed":32,"recovered":30,"tested":28}},"2020-08-16":{"total":{"confirmed":32,"recovered":30,"tested":28}},"2020-08-17":{"delta":{"recovered":2},"total":{"confirmed":32,"recovered":32,"tested":28}},"2020-08-18":{"total":{"confirmed":32,"recovered":32,"tested":28}}}},"Tuensang":{"dates":{"2020-05-19":{"delta":{"tested":1},"total":{"tested":1}},"2020-05-20":{"total":{"tested":1}},"2020-05-21":{"total":{"tested":1}},"2020-05-22":{"total":{"tested":1}},"2020-05-23":{"total":{"tested":1}},"2020-05-24":{"total":{"tested":1}},"2020-05-25":{"total":{"tested":1}},"2020-05-26":{"total":{"tested":1}},"2020-05-27":{"total":{"tested":1}},"2020-05-28":{"delta":{"confirmed":1},"total":{"confirmed":1,"tested":1}},"2020-05-29":{"delta":{"confirmed":1},"total":{"confirmed":2,"tested":1}},"2020-05-30":{"total":{"confirmed":2,"tested":1}},"2020-05-31":{"total":{"confirmed":2,"tested":1}},"2020-06-01":{"total":{"confirmed":2,"tested":1}},"2020-06-02":{"total":{"confirmed":2,"tested":1}},"2020-06-03":{"total":{"confirmed":2,"tested":1}},"2020-06-04":{"delta":{"confirmed":3},"total":{"confirmed":5,"tested":1}},"2020-06-05":{"total":{"confirmed":5,"tested":1}},"2020-06-06":{"delta":{"confirmed":2},"total":{"confirmed":7,"tested":1}},"2020-06-07":{"total":{"confirmed":7,"tested":1}},"2020-06-08":{"delta":{"confirmed":1},"total":{"confirmed":8,"tested":1}},"2020-06-09":{"total":{"confirmed":8,"tested":1}},"2020-06-10":{"total":{"confirmed":8,"tested":1}},"2020-06-11":{"total":{"confirmed":8,"tested":1}},"2020-06-12":{"total":{"confirmed":8,"tested":1}},"2020-06-13":{"total":{"confirmed":8,"tested":1}},"2020-06-14":{"delta":{"confirmed":2},"total":{"confirmed":10,"tested":1}},"2020-06-15":{"total":{"confirmed":10,"tested":1}},"2020-06-16":{"total":{"confirmed":10,"tested":1}},"2020-06-17":{"delta":{"confirmed":1},"total":{"confirmed":11,"tested":1}},"2020-06-18":{"total":{"confirmed":11,"tested":1}},"2020-06-19":{"total":{"confirmed":11,"tested":1}},"2020-06-20":{"total":{"confirmed":11,"tested":1}},"2020-06-21":{"delta":{"confirmed":2},"total":{"confirmed":13,"tested":1}},"2020-06-22":{"total":{"confirmed":13,"tested":1}},"2020-06-23":{"total":{"confirmed":13,"tested":1}},"2020-06-24":{"delta":{"confirmed":2},"total":{"confirmed":15,"tested":1}},"2020-06-25":{"delta":{"confirmed":-2},"total":{"confirmed":13,"tested":1}},"2020-06-26":{"total":{"confirmed":13,"tested":1}},"2020-06-27":{"total":{"confirmed":13,"tested":1}},"2020-06-28":{"total":{"confirmed":13,"tested":1}},"2020-06-29":{"total":{"confirmed":13,"tested":1}},"2020-06-30":{"delta":{"confirmed":17},"total":{"confirmed":30,"tested":1}},"2020-07-01":{"total":{"confirmed":30,"tested":1}},"2020-07-02":{"total":{"confirmed":30,"tested":1}},"2020-07-03":{"total":{"confirmed":30,"tested":1}},"2020-07-04":{"total":{"confirmed":30,"tested":1}},"2020-07-05":{"delta":{"confirmed":2},"total":{"confirmed":32,"tested":1}},"2020-07-06":{"total":{"confirmed":32,"tested":1}},"2020-07-07":{"delta":{"confirmed":8},"total":{"confirmed":40,"tested":1}},"2020-07-08":{"delta":{"confirmed":1},"total":{"confirmed":41,"tested":1}},"2020-07-09":{"total":{"confirmed":41,"tested":1}},"2020-07-10":{"total":{"confirmed":41,"tested":1}},"2020-07-11":{"delta":{"confirmed":5},"total":{"confirmed":46,"tested":1}},"2020-07-12":{"delta":{"confirmed":3},"total":{"confirmed":49,"tested":1}},"2020-07-13":{"total":{"confirmed":49,"tested":1}},"2020-07-14":{"total":{"confirmed":49,"tested":1}},"2020-07-15":{"total":{"confirmed":49,"tested":1}},"2020-07-16":{"total":{"confirmed":49,"tested":1}},"2020-07-17":{"total":{"confirmed":49,"tested":1}},"2020-07-18":{"total":{"confirmed":49,"tested":1}},"2020-07-19":{"total":{"confirmed":49,"tested":1}},"2020-07-20":{"total":{"confirmed":49,"tested":1}},"2020-07-21":{"total":{"confirmed":49,"tested":1}},"2020-07-22":{"total":{"confirmed":49,"tested":1}},"2020-07-23":{"delta":{"recovered":44},"total":{"confirmed":49,"recovered":44,"tested":1}},"2020-07-24":{"delta":{"confirmed":1},"total":{"confirmed":50,"recovered":44,"tested":1}},"2020-07-25":{"delta":{"recovered":-1},"total":{"confirmed":50,"recovered":43,"tested":1}},"2020-07-26":{"total":{"confirmed":50,"recovered":43,"tested":1}},"2020-07-27":{"total":{"confirmed":50,"recovered":43,"tested":1}},"2020-07-28":{"delta":{"confirmed":1},"total":{"confirmed":51,"recovered":43,"tested":1}},"2020-07-29":{"delta":{"recovered":4},"total":{"confirmed":51,"recovered":47,"tested":1}},"2020-07-30":{"total":{"confirmed":51,"recovered":47,"tested":1}},"2020-07-31":{"total":{"confirmed":51,"recovered":47,"tested":1}},"2020-08-01":{"total":{"confirmed":51,"recovered":47,"tested":1}},"2020-08-02":{"total":{"confirmed":51,"recovered":47,"tested":1}},"2020-08-03":{"total":{"confirmed":51,"recovered":47,"tested":1}},"2020-08-04":{"total":{"confirmed":51,"recovered":47,"tested":1}},"2020-08-05":{"total":{"confirmed":51,"recovered":47,"tested":1}},"2020-08-06":{"delta":{"recovered":3},"total":{"confirmed":51,"recovered":50,"tested":1}},"2020-08-07":{"total":{"confirmed":51,"recovered":50,"tested":1}},"2020-08-08":{"total":{"confirmed":51,"recovered":50,"tested":1}},"2020-08-09":{"total":{"confirmed":51,"recovered":50,"tested":1}},"2020-08-10":{"total":{"confirmed":51,"recovered":50,"tested":1}},"2020-08-11":{"delta":{"confirmed":1},"total":{"confirmed":52,"recovered":50,"tested":1}},"2020-08-12":{"total":{"confirmed":52,"recovered":50,"tested":1}},"2020-08-13":{"total":{"confirmed":52,"recovered":50,"tested":1}},"2020-08-14":{"total":{"confirmed":52,"recovered":50,"tested":1}},"2020-08-15":{"delta":{"confirmed":1},"total":{"confirmed":53,"recovered":50,"tested":1}},"2020-08-16":{"total":{"confirmed":53,"recovered":50,"tested":1}},"2020-08-17":{"total":{"confirmed":53,"recovered":50,"tested":1}},"2020-08-18":{"total":{"confirmed":53,"recovered":50,"tested":1}}}},"Unknown":{"dates":{"2020-06-03":{"delta":{"confirmed":9},"total":{"confirmed":9}},"2020-06-04":{"delta":{"confirmed":-9}},"2020-06-05":{"delta":{"confirmed":27},"total":{"confirmed":27}},"2020-06-06":{"delta":{"confirmed":-27}},"2020-06-12":{"delta":{"recovered":20},"total":{"recovered":20}},"2020-06-13":{"delta":{"confirmed":7},"total":{"confirmed":7,"recovered":20}},"2020-06-14":{"delta":{"confirmed":5,"recovered":68},"total":{"confirmed":12,"recovered":88}},"2020-06-15":{"delta":{"confirmed":-12},"total":{"recovered":88}},"2020-06-16":{"delta":{"recovered":15},"total":{"recovered":103}},"2020-06-17":{"total":{"recovered":103}},"2020-06-18":{"total":{"recovered":103}},"2020-06-19":{"delta":{"recovered":16},"total":{"recovered":119}},"2020-06-20":{"delta":{"recovered":13},"total":{"recovered":132}},"2020-06-21":{"delta":{"recovered":3},"total":{"recovered":135}},"2020-06-22":{"total":{"recovered":135}},"2020-06-23":{"total":{"recovered":135}},"2020-06-24":{"total":{"recovered":135}},"2020-06-25":{"total":{"recovered":135}},"2020-06-26":{"delta":{"confirmed":16},"total":{"confirmed":16,"recovered":135}},"2020-06-27":{"delta":{"confirmed":-16},"total":{"recovered":135}},"2020-06-28":{"total":{"recovered":135}},"2020-06-29":{"delta":{"confirmed":17,"recovered":4},"total":{"confirmed":17,"recovered":139}},"2020-06-30":{"delta":{"confirmed":-17},"total":{"recovered":139}},"2020-07-01":{"delta":{"recovered":14},"total":{"recovered":153}},"2020-07-02":{"delta":{"recovered":15},"total":{"recovered":168}},"2020-07-03":{"total":{"recovered":168}},"2020-07-04":{"delta":{"confirmed":1},"total":{"confirmed":1,"recovered":168}},"2020-07-05":{"delta":{"confirmed":-1,"recovered":3},"total":{"recovered":171}},"2020-07-06":{"delta":{"recovered":12},"total":{"recovered":183}},"2020-07-07":{"delta":{"recovered":60},"total":{"recovered":243}},"2020-07-08":{"delta":{"recovered":1},"total":{"recovered":244}},"2020-07-09":{"total":{"recovered":244}},"2020-07-10":{"total":{"recovered":244}},"2020-07-11":{"delta":{"recovered":9},"total":{"recovered":253}},"2020-07-12":{"total":{"recovered":253}},"2020-07-13":{"delta":{"recovered":13},"total":{"recovered":266}},"2020-07-14":{"delta":{"recovered":6},"total":{"recovered":272}},"2020-07-15":{"total":{"recovered":272}},"2020-07-16":{"total":{"recovered":272}},"2020-07-17":{"total":{"recovered":272}},"2020-07-18":{"delta":{"recovered":27},"total":{"recovered":299}},"2020-07-19":{"delta":{"recovered":13},"total":{"recovered":312}},"2020-07-20":{"delta":{"recovered":39},"total":{"recovered":351}},"2020-07-21":{"delta":{"recovered":1},"total":{"recovered":352}},"2020-07-22":{"delta":{"recovered":1},"total":{"recovered":353}},"2020-07-23":{"delta":{"recovered":-353}}}},"Wokha":{"dates":{"2020-05-19":{"delta":{"tested":7},"total":{"tested":7}},"2020-05-20":{"total":{"tested":7}},"2020-05-21":{"total":{"tested":7}},"2020-05-22":{"total":{"tested":7}},"2020-05-23":{"total":{"tested":7}},"2020-05-24":{"total":{"tested":7}},"2020-05-25":{"total":{"tested":7}},"2020-05-26":{"total":{"tested":7}},"2020-05-27":{"total":{"tested":7}},"2020-05-28":{"total":{"tested":7}},"2020-05-29":{"total":{"tested":7}},"2020-05-30":{"total":{"tested":7}},"2020-05-31":{"total":{"tested":7}},"2020-06-01":{"total":{"tested":7}},"2020-06-02":{"total":{"tested":7}},"2020-06-03":{"total":{"tested":7}},"2020-06-04":{"total":{"tested":7}},"2020-06-05":{"total":{"tested":7}},"2020-06-06":{"delta":{"confirmed":5},"total":{"confirmed":5,"tested":7}},"2020-06-07":{"total":{"confirmed":5,"tested":7}},"2020-06-08":{"total":{"confirmed":5,"tested":7}},"2020-06-09":{"total":{"confirmed":5,"tested":7}},"2020-06-10":{"total":{"confirmed":5,"tested":7}},"2020-06-11":{"total":{"confirmed":5,"tested":7}},"2020-06-12":{"total":{"confirmed":5,"tested":7}},"2020-06-13":{"total":{"confirmed":5,"tested":7}},"2020-06-14":{"delta":{"confirmed":-5},"total":{"tested":7}},"2020-06-15":{"delta":{"confirmed":7},"total":{"confirmed":7,"tested":7}},"2020-06-16":{"delta":{"confirmed":1},"total":{"confirmed":8,"tested":7}},"2020-06-17":{"total":{"confirmed":8,"tested":7}},"2020-06-18":{"total":{"confirmed":8,"tested":7}},"2020-06-19":{"total":{"confirmed":8,"tested":7}},"2020-06-20":{"total":{"confirmed":8,"tested":7}},"2020-06-21":{"delta":{"confirmed":1},"total":{"confirmed":9,"tested":7}},"2020-06-22":{"total":{"confirmed":9,"tested":7}},"2020-06-23":{"total":{"confirmed":9,"tested":7}},"2020-06-24":{"delta":{"confirmed":1},"total":{"confirmed":10,"tested":7}},"2020-06-25":{"total":{"confirmed":10,"tested":7}},"2020-06-26":{"total":{"confirmed":10,"tested":7}},"2020-06-27":{"total":{"confirmed":10,"tested":7}},"2020-06-28":{"total":{"confirmed":10,"tested":7}},"2020-06-29":{"total":{"confirmed":10,"tested":7}},"2020-06-30":{"total":{"confirmed":10,"tested":7}},"2020-07-01":{"total":{"confirmed":10,"tested":7}},"2020-07-02":{"total":{"confirmed":10,"tested":7}},"2020-07-03":{"total":{"confirmed":10,"tested":7}},"2020-07-04":{"total":{"confirmed":10,"tested":7}},"2020-07-05":{"total":{"confirmed":10,"tested":7}},"2020-07-06":{"total":{"confirmed":10,"tested":7}},"2020-07-07":{"total":{"confirmed":10,"tested":7}},"2020-07-08":{"total":{"confirmed":10,"tested":7}},"2020-07-09":{"total":{"confirmed":10,"tested":7}},"2020-07-10":{"delta":{"confirmed":1},"total":{"confirmed":11,"tested":7}},"2020-07-11":{"total":{"confirmed":11,"tested":7}},"2020-07-12":{"total":{"confirmed":11,"tested":7}},"2020-07-13":{"total":{"confirmed":11,"tested":7}},"2020-07-14":{"total":{"confirmed":11,"tested":7}},"2020-07-15":{"total":{"confirmed":11,"tested":7}},"2020-07-16":{"total":{"confirmed":11,"tested":7}},"2020-07-17":{"total":{"confirmed":11,"tested":7}},"2020-07-18":{"total":{"confirmed":11,"tested":7}},"2020-07-19":{"total":{"confirmed":11,"tested":7}},"2020-07-20":{"total":{"confirmed":11,"tested":7}},"2020-07-21":{"total":{"confirmed":11,"tested":7}},"2020-07-22":{"total":{"confirmed":11,"tested":7}},"2020-07-23":{"delta":{"recovered":10},"total":{"confirmed":11,"recovered":10,"tested":7}},"2020-07-24":{"total":{"confirmed":11,"recovered":10,"tested":7}},"2020-07-25":{"total":{"confirmed":11,"recovered":10,"tested":7}},"2020-07-26":{"total":{"confirmed":11,"recovered":10,"tested":7}},"2020-07-27":{"delta":{"recovered":1},"total":{"confirmed":11,"recovered":11,"tested":7}},"2020-07-28":{"delta":{"confirmed":7},"total":{"confirmed":18,"recovered":11,"tested":7}},"2020-07-29":{"total":{"confirmed":18,"recovered":11,"tested":7}},"2020-07-30":{"total":{"confirmed":18,"recovered":11,"tested":7}},"2020-07-31":{"total":{"confirmed":18,"recovered":11,"tested":7}},"2020-08-01":{"total":{"confirmed":18,"recovered":11,"tested":7}},"2020-08-02":{"delta":{"confirmed":5},"total":{"confirmed":23,"recovered":11,"tested":7}},"2020-08-03":{"total":{"confirmed":23,"recovered":11,"tested":7}},"2020-08-04":{"total":{"confirmed":23,"recovered":11,"tested":7}},"2020-08-05":{"total":{"confirmed":23,"recovered":11,"tested":7}},"2020-08-06":{"total":{"confirmed":23,"recovered":11,"tested":7}},"2020-08-07":{"total":{"confirmed":23,"recovered":11,"tested":7}},"2020-08-08":{"delta":{"confirmed":3,"recovered":1},"total":{"confirmed":26,"recovered":12,"tested":7}},"2020-08-09":{"delta":{"recovered":4},"total":{"confirmed":26,"recovered":16,"tested":7}},"2020-08-10":{"delta":{"recovered":2},"total":{"confirmed":26,"recovered":18,"tested":7}},"2020-08-11":{"total":{"confirmed":26,"recovered":18,"tested":7}},"2020-08-12":{"delta":{"confirmed":1},"total":{"confirmed":27,"recovered":18,"tested":7}},"2020-08-13":{"total":{"confirmed":27,"recovered":18,"tested":7}},"2020-08-14":{"delta":{"confirmed":1,"recovered":2},"total":{"confirmed":28,"recovered":20,"tested":7}},"2020-08-15":{"delta":{"confirmed":1},"total":{"confirmed":29,"recovered":20,"tested":7}},"2020-08-16":{"total":{"confirmed":29,"recovered":20,"tested":7}},"2020-08-17":{"total":{"confirmed":29,"recovered":20,"tested":7}},"2020-08-18":{"total":{"confirmed":29,"recovered":20,"tested":7}}}},"Zunheboto":{"dates":{"2020-06-08":{"delta":{"confirmed":1},"total":{"confirmed":1}},"2020-06-09":{"total":{"confirmed":1}},"2020-06-10":{"total":{"confirmed":1}},"2020-06-11":{"total":{"confirmed":1}},"2020-06-12":{"total":{"confirmed":1}},"2020-06-13":{"total":{"confirmed":1}},"2020-06-14":{"total":{"confirmed":1}},"2020-06-15":{"total":{"confirmed":1}},"2020-06-16":{"total":{"confirmed":1}},"2020-06-17":{"total":{"confirmed":1}},"2020-06-18":{"total":{"confirmed":1}},"2020-06-19":{"total":{"confirmed":1}},"2020-06-20":{"total":{"confirmed":1}},"2020-06-21":{"total":{"confirmed":1}},"2020-06-22":{"delta":{"confirmed":1},"total":{"confirmed":2}},"2020-06-23":{"delta":{"confirmed":1},"total":{"confirmed":3}},"2020-06-24":{"delta":{"confirmed":2},"total":{"confirmed":5}},"2020-06-25":{"total":{"confirmed":5}},"2020-06-26":{"total":{"confirmed":5}},"2020-06-27":{"total":{"confirmed":5}},"2020-06-28":{"total":{"confirmed":5}},"2020-06-29":{"total":{"confirmed":5}},"2020-06-30":{"total":{"confirmed":5}},"2020-07-01":{"total":{"confirmed":5}},"2020-07-02":{"total":{"confirmed":5}},"2020-07-03":{"total":{"confirmed":5}},"2020-07-04":{"total":{"confirmed":5}},"2020-07-05":{"delta":{"confirmed":1},"total":{"confirmed":6}},"2020-07-06":{"total":{"confirmed":6}},"2020-07-07":{"total":{"confirmed":6}},"2020-07-08":{"total":{"confirmed":6}},"2020-07-09":{"total":{"confirmed":6}},"2020-07-10":{"total":{"confirmed":6}},"2020-07-11":{"total":{"confirmed":6}},"2020-07-12":{"total":{"confirmed":6}},"2020-07-13":{"total":{"confirmed":6}},"2020-07-14":{"delta":{"confirmed":1},"total":{"confirmed":7}},"2020-07-15":{"total":{"confirmed":7}},"2020-07-16":{"total":{"confirmed":7}},"2020-07-17":{"total":{"confirmed":7}},"2020-07-18":{"total":{"confirmed":7}},"2020-07-19":{"total":{"confirmed":7}},"2020-07-20":{"total":{"confirmed":7}},"2020-07-21":{"total":{"confirmed":7}},"2020-07-22":{"delta":{"confirmed":7},"total":{"confirmed":14}},"2020-07-23":{"delta":{"recovered":6},"total":{"confirmed":14,"recovered":6}},"2020-07-24":{"total":{"confirmed":14,"recovered":6}},"2020-07-25":{"total":{"confirmed":14,"recovered":6}},"2020-07-26":{"total":{"confirmed":14,"recovered":6}},"2020-07-27":{"total":{"confirmed":14,"recovered":6}},"2020-07-28":{"total":{"confirmed":14,"recovered":6}},"2020-07-29":{"total":{"confirmed":14,"recovered":6}},"2020-07-30":{"total":{"confirmed":14,"recovered":6}},"2020-07-31":{"total":{"confirmed":14,"recovered":6}},"2020-08-01":{"delta":{"recovered":1},"total":{"confirmed":14,"recovered":7}},"2020-08-02":{"delta":{"confirmed":18},"total":{"confirmed":32,"recovered":7}},"2020-08-03":{"delta":{"confirmed":36},"total":{"confirmed":68,"recovered":7}},"2020-08-04":{"total":{"confirmed":68,"recovered":7}},"2020-08-05":{"delta":{"recovered":3},"total":{"confirmed":68,"recovered":10}},"2020-08-06":{"delta":{"recovered":1},"total":{"confirmed":68,"recovered":11}},"2020-08-07":{"delta":{"recovered":5},"total":{"confirmed":68,"recovered":16}},"2020-08-08":{"delta":{"confirmed":6},"total":{"confirmed":74,"recovered":16}},"2020-08-09":{"delta":{"confirmed":1},"total":{"confirmed":75,"recovered":16}},"2020-08-10":{"total":{"confirmed":75,"recovered":16}},"2020-08-11":{"total":{"confirmed":75,"recovered":16}},"2020-08-12":{"delta":{"confirmed":3,"recovered":2},"total":{"confirmed":78,"recovered":18}},"2020-08-13":{"delta":{"confirmed":5},"total":{"confirmed":83,"recovered":18}},"2020-08-14":{"delta":{"confirmed":10},"total":{"confirmed":93,"recovered":18}},"2020-08-15":{"total":{"confirmed":93,"recovered":18}},"2020-08-16":{"delta":{"confirmed":7},"total":{"confirmed":100,"recovered":18}},"2020-08-17":{"delta":{"confirmed":2},"total":{"confirmed":102,"recovered":18}},"2020-08-18":{"delta":{"recovered":19},"total":{"confirmed":102,"recovered":37}}}}}}}