{"SK":{"dates":{"2020-05-04":{"delta":{"tested":{"samples":170}},"total":{"tested":{"samples":170}}},"2020-05-05":{"delta":{"tested":{"samples":11}},"total":{"tested":{"samples":181}}},"2020-05-06":{"delta":{"tested":{"samples":8}},"total":{"tested":{"samples":189}}},"2020-05-07":{"delta":{"tested":{"samples":27}},"total":{"tested":{"samples":216}}},"2020-05-08":{"total":{"tested":{"samples":216}}},"2020-05-09":{"delta":{"tested":{"samples":3}},"total":{"tested":{"samples":219}}},"2020-05-10":{"total":{"tested":{"samples":219}}},"2020-05-11":{"total":{"tested":{"samples":219}}},"2020-05-12":{"delta":{"tested":{"samples":129}},"total":{"tested":{"samples":348}}},"2020-05-13":{"delta":{"tested":{"samples":91}},"total":{"tested":{"samples":439}}},"2020-05-14":{"delta":{"tested":{"samples":140}},"total":{"tested":{"samples":579}}},"2020-05-15":{"delta":{"tested":{"samples":-231}},"total":{"tested":{"samples":348}}},"2020-05-16":{"delta":{"tested":{"samples":492}},"total":{"tested":{"samples":840}}},"2020-05-17":{"delta":{"tested":{"samples":107}},"total":{"tested":{"samples":947}}},"2020-05-18":{"delta":{"tested":{"samples":140}},"total":{"tested":{"samples":1087}}},"2020-05-19":{"delta":{"tested":{"samples":117}},"total":{"tested":{"samples":1204}}},"2020-05-20":{"delta":{"tested":{"samples":138}},"total":{"tested":{"samples":1342}}},"2020-05-21":{"total":{"tested":{"samples":1342}}},"2020-05-22":{"delta":{"tested":{"samples":295}},"total":{"tested":{"samples":1637}}},"2020-05-23":{"delta":{"confirmed":1,"tested":{"samples":70}},"total":{"confirmed":1,"tested":{"samples":1707}}},"2020-05-24":{"delta":{"tested":{"positives":1,"samples":148}},"total":{"confirmed":1,"tested":{"positives":1,"samples":1855}}},"2020-05-25":{"delta":{"tested":{"samples":248}},"total":{"confirmed":1,"tested":{"positives":1,"samples":2103}}},"2020-05-26":{"delta":{"tested":{"samples":152}},"total":{"confirmed":1,"tested":{"positives":1,"samples":2255}}},"2020-05-27":{"delta":{"tested":{"samples":162}},"total":{"confirmed":1,"tested":{"positives":1,"samples":2417}}},"2020-05-28":{"delta":{"tested":{"samples":209}},"total":{"confirmed":1,"tested":{"positives":1,"samples":2626}}},"2020-05-29":{"delta":{"tested":{"samples":133}},"total":{"confirmed":1,"tested":{"positives":1,"samples":2759}}},"2020-05-30":{"delta":{"tested":{"samples":70}},"total":{"confirmed":1,"tested":{"positives":1,"samples":2829}}},"2020-05-31":{"delta":{"tested":{"samples":96}},"total":{"confirmed":1,"tested":{"positives":1,"samples":2925}}},"2020-06-01":{"delta":{"tested":{"samples":600}},"total":{"confirmed":1,"tested":{"positives":1,"samples":3525}}},"2020-06-02":{"delta":{"tested":{"samples":263}},"total":{"confirmed":1,"tested":{"positives":1,"samples":3788}}},"2020-06-03":{"delta":{"confirmed":1,"tested":{"positives":1,"samples":314}},"total":{"confirmed":2,"tested":{"positives":2,"samples":4102}}},"2020-06-04":{"delta":{"tested":{"samples":256}},"total":{"confirmed":2,"tested":{"positives":2,"samples":4358}}},"2020-06-05":{"delta":{"confirmed":1,"tested":{"positives":1,"samples":403}},"total":{"confirmed":3,"tested":{"positives":3,"samples":4761}}},"2020-06-06":{"delta":{"confirmed":4,"tested":{"samples":244}},"total":{"confirmed":7,"tested":{"positives":3,"samples":5005}}},"2020-06-07":{"total":{"confirmed":7,"tested":{"positives":3,"samples":5005}}},"2020-06-08":{"delta":{"tested":{"positives":3,"samples":542}},"total":{"confirmed":7,"tested":{"positives":6,"samples":5547}}},"2020-06-09":{"delta":{"confirmed":6,"recovered":3,"tested":{"positives":6,"samples":268}},"total":{"confirmed":13,"recovered":3,"tested":{"positives":12,"samples":5815}}},"2020-06-10":{"delta":{"tested":{"samples":346}},"total":{"confirmed":13,"recovered":3,"tested":{"positives":12,"samples":6161}}},"2020-06-11":{"delta":{"tested":{"samples":531}},"total":{"confirmed":13,"recovered":3,"tested":{"positives":12,"samples":6692}}},"2020-06-12":{"delta":{"confirmed":50,"tested":{"positives":14,"samples":-1535}},"total":{"confirmed":63,"recovered":3,"tested":{"positives":26,"samples":5157}}},"2020-06-13":{"delta":{"recovered":1,"tested":{"positives":36,"samples":220}},"total":{"confirmed":63,"recovered":4,"tested":{"positives":62,"samples":5377}}},"2020-06-14":{"delta":{"confirmed":5,"tested":{"positives":5,"samples":287}},"total":{"confirmed":68,"recovered":4,"tested":{"positives":67,"samples":5664}}},"2020-06-15":{"delta":{"tested":{"positives":1,"samples":98}},"total":{"confirmed":68,"recovered":4,"tested":{"positives":68,"samples":5762}}},"2020-06-16":{"delta":{"tested":{"samples":430}},"total":{"confirmed":68,"recovered":4,"tested":{"positives":68,"samples":6192}}},"2020-06-17":{"delta":{"confirmed":2,"tested":{"positives":2,"samples":157}},"total":{"confirmed":70,"recovered":4,"tested":{"positives":70,"samples":6349}}},"2020-06-18":{"delta":{"recovered":1},"total":{"confirmed":70,"recovered":5,"tested":{"positives":70,"samples":6349}}},"2020-06-19":{"delta":{"recovered":16,"tested":{"samples":533}},"total":{"confirmed":70,"recovered":21,"tested":{"positives":70,"samples":6882}}},"2020-06-20":{"delta":{"tested":{"samples":301}},"total":{"confirmed":70,"recovered":21,"tested":{"positives":70,"samples":7183}}},"2020-06-21":{"delta":{"confirmed":8,"recovered":4,"tested":{"samples":2171}},"total":{"confirmed":78,"recovered":25,"tested":{"positives":70,"samples":9354}}},"2020-06-22":{"delta":{"recovered":4,"tested":{"positives":8,"samples":95}},"total":{"confirmed":78,"recovered":29,"tested":{"positives":78,"samples":9449}}},"2020-06-23":{"delta":{"confirmed":1,"tested":{"positives":1,"samples":145}},"total":{"confirmed":79,"recovered":29,"tested":{"positives":79,"samples":9594}}},"2020-06-24":{"delta":{"confirmed":4,"recovered":10,"tested":{"positives":4,"samples":255}},"total":{"confirmed":83,"recovered":39,"tested":{"positives":83,"samples":9849}}},"2020-06-25":{"delta":{"confirmed":2,"tested":{"positives":2,"samples":176}},"total":{"confirmed":85,"recovered":39,"tested":{"positives":85,"samples":10025}}},"2020-06-26":{"delta":{"confirmed":2,"tested":{"positives":1,"samples":187}},"total":{"confirmed":87,"recovered":39,"tested":{"positives":86,"samples":10212}}},"2020-06-27":{"delta":{"recovered":10,"tested":{"positives":1,"samples":7}},"total":{"confirmed":87,"recovered":49,"tested":{"positives":87,"samples":10219}}},"2020-06-28":{"delta":{"confirmed":1,"tested":{"positives":1,"samples":145}},"total":{"confirmed":88,"recovered":49,"tested":{"positives":88,"samples":10364}}},"2020-06-29":{"delta":{"tested":{"samples":76}},"total":{"confirmed":88,"recovered":49,"tested":{"positives":88,"samples":10440}}},"2020-06-30":{"delta":{"recovered":1,"tested":{"samples":95}},"total":{"confirmed":88,"recovered":50,"tested":{"positives":88,"samples":10535}}},"2020-07-01":{"delta":{"confirmed":1,"recovered":2,"tested":{"samples":188}},"total":{"confirmed":89,"recovered":52,"tested":{"positives":88,"samples":10723}}},"2020-07-02":{"delta":{"confirmed":12,"tested":{"samples":177}},"total":{"confirmed":101,"recovered":52,"tested":{"positives":88,"samples":10900}}},"2020-07-03":{"delta":{"confirmed":1,"tested":{"positives":13,"samples":172}},"total":{"confirmed":102,"recovered":52,"tested":{"positives":101,"samples":11072}}},"2020-07-04":{"delta":{"confirmed":1,"tested":{"positives":2,"samples":170}},"total":{"confirmed":103,"recovered":52,"tested":{"positives":103,"samples":11242}}},"2020-07-05":{"delta":{"confirmed":22,"other":13,"recovered":9,"tested":{"positives":22,"samples":145}},"total":{"confirmed":125,"other":13,"recovered":61,"tested":{"positives":125,"samples":11387}}},"2020-07-06":{"delta":{"recovered":4,"tested":{"samples":20}},"total":{"confirmed":125,"other":13,"recovered":65,"tested":{"positives":125,"samples":11407}}},"2020-07-07":{"delta":{"confirmed":2,"tested":{"samples":174}},"total":{"confirmed":127,"other":13,"recovered":65,"tested":{"positives":125,"samples":11581}}},"2020-07-08":{"delta":{"confirmed":6,"recovered":6,"tested":{"positives":4,"samples":239}},"total":{"confirmed":133,"other":13,"recovered":71,"tested":{"positives":129,"samples":11820}}},"2020-07-09":{"delta":{"confirmed":1,"tested":{"positives":1,"samples":192}},"total":{"confirmed":134,"other":13,"recovered":71,"tested":{"positives":130,"samples":12012}}},"2020-07-10":{"delta":{"confirmed":-13,"other":-13,"recovered":9,"tested":{"samples":107}},"total":{"confirmed":121,"recovered":80,"tested":{"positives":130,"samples":12119}}},"2020-07-11":{"delta":{"confirmed":26,"tested":{"positives":26,"samples":127}},"total":{"confirmed":147,"recovered":80,"tested":{"positives":156,"samples":12246}}},"2020-07-12":{"delta":{"confirmed":4,"recovered":1,"tested":{"positives":4,"samples":285}},"total":{"confirmed":151,"recovered":81,"tested":{"positives":160,"samples":12531}}},"2020-07-13":{"delta":{"confirmed":2,"recovered":6,"tested":{"positives":2,"samples":105}},"total":{"confirmed":153,"recovered":87,"tested":{"positives":162,"samples":12636}}},"2020-07-14":{"delta":{"confirmed":45,"recovered":-1,"tested":{"positives":49,"samples":303}},"total":{"confirmed":198,"recovered":86,"tested":{"positives":211,"samples":12939}}},"2020-07-15":{"delta":{"confirmed":11,"recovered":1,"tested":{"samples":413}},"total":{"confirmed":209,"recovered":87,"tested":{"positives":211,"samples":13352}}},"2020-07-16":{"delta":{"confirmed":13,"tested":{"positives":24,"samples":410}},"total":{"confirmed":222,"recovered":87,"tested":{"positives":235,"samples":13762}}},"2020-07-17":{"delta":{"confirmed":32,"recovered":1,"tested":{"positives":19,"samples":611}},"total":{"confirmed":254,"recovered":88,"tested":{"positives":254,"samples":14373}}},"2020-07-18":{"delta":{"confirmed":19,"recovered":2,"tested":{"positives":19,"samples":766}},"total":{"confirmed":273,"recovered":90,"tested":{"positives":273,"samples":15139}}},"2020-07-19":{"delta":{"confirmed":10,"tested":{"positives":10,"samples":818}},"total":{"confirmed":283,"recovered":90,"tested":{"positives":283,"samples":15957}}},"2020-07-20":{"delta":{"confirmed":22,"recovered":2,"tested":{"positives":22,"samples":949}},"total":{"confirmed":305,"recovered":92,"tested":{"positives":305,"samples":16906}}},"2020-07-21":{"delta":{"confirmed":25,"recovered":16,"tested":{"positives":25,"samples":658}},"total":{"confirmed":330,"recovered":108,"tested":{"positives":330,"samples":17564}}},"2020-07-22":{"delta":{"confirmed":108,"recovered":4,"tested":{"positives":108,"samples":1920}},"total":{"confirmed":438,"recovered":112,"tested":{"positives":438,"samples":19484}}},"2020-07-23":{"delta":{"confirmed":22,"recovered":10,"tested":{"positives":22,"samples":566}},"total":{"confirmed":460,"recovered":122,"tested":{"positives":460,"samples":20050}}},"2020-07-24":{"delta":{"confirmed":17,"recovered":15,"tested":{"positives":17,"samples":735}},"total":{"confirmed":477,"recovered":137,"tested":{"positives":477,"samples":20785}}},"2020-07-25":{"delta":{"confirmed":22,"recovered":5,"tested":{"positives":35,"samples":487}},"total":{"confirmed":499,"recovered":142,"tested":{"positives":512,"samples":21272}}},"2020-07-26":{"delta":{"confirmed":46,"deceased":1,"recovered":5},"total":{"confirmed":545,"deceased":1,"recovered":147,"tested":{"positives":512,"samples":21272}}},"2020-07-27":{"delta":{"confirmed":10,"recovered":27,"tested":{"positives":33,"samples":1138}},"total":{"confirmed":555,"deceased":1,"recovered":174,"tested":{"positives":545,"samples":22410}}},"2020-07-28":{"delta":{"confirmed":24,"recovered":12,"tested":{"positives":34,"samples":583}},"total":{"confirmed":579,"deceased":1,"recovered":186,"tested":{"positives":579,"samples":22993}}},"2020-07-29":{"delta":{"confirmed":17,"recovered":12,"tested":{"positives":17,"samples":644}},"total":{"confirmed":596,"deceased":1,"recovered":198,"tested":{"positives":596,"samples":23637}}},"2020-07-30":{"delta":{"confirmed":14,"recovered":16,"tested":{"positives":14,"samples":513}},"total":{"confirmed":610,"deceased":1,"recovered":214,"tested":{"positives":610,"samples":24150}}},"2020-07-31":{"delta":{"confirmed":29,"recovered":17,"tested":{"positives":29,"samples":789}},"total":{"confirmed":639,"deceased":1,"recovered":231,"tested":{"positives":639,"samples":24939}}},"2020-08-01":{"delta":{"confirmed":11,"recovered":38,"tested":{"positives":11,"samples":977}},"total":{"confirmed":650,"deceased":1,"recovered":269,"tested":{"positives":650,"samples":25916}}},"2020-08-02":{"delta":{"confirmed":8,"recovered":20,"tested":{"positives":8,"samples":557}},"total":{"confirmed":658,"deceased":1,"recovered":289,"tested":{"positives":658,"samples":26473}}},"2020-08-03":{"delta":{"confirmed":30,"recovered":8,"tested":{"positives":30,"samples":642}},"total":{"confirmed":688,"deceased":1,"recovered":297,"tested":{"positives":688,"samples":27115}}},"2020-08-04":{"delta":{"confirmed":95,"recovered":2},"total":{"confirmed":783,"deceased":1,"recovered":299,"tested":{"positives":688,"samples":27115}}}},"districts":{"East Sikkim":{"dates":{"2020-06-03":{"delta":{"confirmed":1},"total":{"confirmed":1}},"2020-06-04":{"total":{"confirmed":1}},"2020-06-05":{"delta":{"confirmed":1},"total":{"confirmed":2}},"2020-06-06":{"delta":{"confirmed":1},"total":{"confirmed":3}},"2020-06-07":{"total":{"confirmed":3}},"2020-06-08":{"total":{"confirmed":3}},"2020-06-09":{"delta":{"recovered":3},"total":{"confirmed":3,"recovered":3}},"2020-06-10":{"total":{"confirmed":3,"recovered":3}},"2020-06-11":{"total":{"confirmed":3,"recovered":3}},"2020-06-12":{"delta":{"confirmed":14},"total":{"confirmed":17,"recovered":3}},"2020-06-13":{"delta":{"confirmed":10,"recovered":1},"total":{"confirmed":27,"recovered":4}},"2020-06-14":{"delta":{"confirmed":-7},"total":{"confirmed":20,"recovered":4}},"2020-06-15":{"total":{"confirmed":20,"recovered":4}},"2020-06-16":{"total":{"confirmed":20,"recovered":4}},"2020-06-17":{"delta":{"confirmed":1},"total":{"confirmed":21,"recovered":4}},"2020-06-18":{"delta":{"recovered":1},"total":{"confirmed":21,"recovered":5}},"2020-06-19":{"delta":{"recovered":-3},"total":{"confirmed":21,"recovered":2}},"2020-06-20":{"total":{"confirmed":21,"recovered":2}},"2020-06-21":{"delta":{"confirmed":4},"total":{"confirmed":25,"recovered":2}},"2020-06-22":{"total":{"confirmed":25,"recovered":2}},"2020-06-23":{"total":{"confirmed":25,"recovered":2}},"2020-06-24":{"delta":{"recovered":1},"total":{"confirmed":25,"recovered":3}},"2020-06-25":{"delta":{"confirmed":1},"total":{"confirmed":26,"recovered":3}},"2020-06-26":{"delta":{"confirmed":1},"total":{"confirmed":27,"recovered":3}},"2020-06-27":{"delta":{"recovered":9},"total":{"confirmed":27,"recovered":12}},"2020-06-28":{"delta":{"confirmed":1},"total":{"confirmed":28,"recovered":12}},"2020-06-29":{"total":{"confirmed":28,"recovered":12}},"2020-06-30":{"total":{"confirmed":28,"recovered":12}},"2020-07-01":{"delta":{"confirmed":1},"total":{"confirmed":29,"recovered":12}},"2020-07-02":{"delta":{"confirmed":12,"recovered":2},"total":{"confirmed":41,"recovered":14}},"2020-07-03":{"total":{"confirmed":41,"recovered":14}},"2020-07-04":{"delta":{"confirmed":2},"total":{"confirmed":43,"recovered":14}},"2020-07-05":{"delta":{"confirmed":22,"other":13,"recovered":9},"total":{"confirmed":65,"other":13,"recovered":23}},"2020-07-06":{"delta":{"recovered":4},"total":{"confirmed":65,"other":13,"recovered":27}},"2020-07-07":{"delta":{"confirmed":2},"total":{"confirmed":67,"other":13,"recovered":27}},"2020-07-08":{"delta":{"confirmed":6,"recovered":6},"total":{"confirmed":73,"other":13,"recovered":33}},"2020-07-09":{"delta":{"confirmed":1},"total":{"confirmed":74,"other":13,"recovered":33}},"2020-07-10":{"delta":{"confirmed":-13,"other":-13,"recovered":9},"total":{"confirmed":61,"recovered":42}},"2020-07-11":{"delta":{"confirmed":26},"total":{"confirmed":87,"recovered":42}},"2020-07-12":{"delta":{"confirmed":4,"recovered":1},"total":{"confirmed":91,"recovered":43}},"2020-07-13":{"delta":{"confirmed":1,"recovered":6},"total":{"confirmed":92,"recovered":49}},"2020-07-14":{"delta":{"confirmed":39,"recovered":-1},"total":{"confirmed":131,"recovered":48}},"2020-07-15":{"delta":{"confirmed":11,"recovered":1},"total":{"confirmed":142,"recovered":49}},"2020-07-16":{"delta":{"confirmed":13},"total":{"confirmed":155,"recovered":49}},"2020-07-17":{"delta":{"confirmed":25,"recovered":1},"total":{"confirmed":180,"recovered":50}},"2020-07-18":{"delta":{"confirmed":19,"recovered":2},"total":{"confirmed":199,"recovered":52}},"2020-07-19":{"delta":{"confirmed":10},"total":{"confirmed":209,"recovered":52}},"2020-07-20":{"delta":{"confirmed":22,"recovered":2},"total":{"confirmed":231,"recovered":54}},"2020-07-21":{"delta":{"confirmed":24,"recovered":16},"total":{"confirmed":255,"recovered":70}},"2020-07-22":{"delta":{"confirmed":61,"recovered":4},"total":{"confirmed":316,"recovered":74}},"2020-07-23":{"delta":{"confirmed":19},"total":{"confirmed":335,"recovered":74}},"2020-07-24":{"delta":{"confirmed":11},"total":{"confirmed":346,"recovered":74}},"2020-07-25":{"total":{"confirmed":346,"recovered":74}},"2020-07-26":{"delta":{"deceased":1},"total":{"confirmed":346,"deceased":1,"recovered":74}},"2020-07-27":{"total":{"confirmed":346,"deceased":1,"recovered":74}},"2020-07-28":{"delta":{"confirmed":8},"total":{"confirmed":354,"deceased":1,"recovered":74}},"2020-07-29":{"delta":{"confirmed":43,"recovered":51},"total":{"confirmed":397,"deceased":1,"recovered":125}},"2020-07-30":{"delta":{"confirmed":28,"recovered":8},"total":{"confirmed":425,"deceased":1,"recovered":133}},"2020-07-31":{"delta":{"confirmed":28,"recovered":17},"total":{"confirmed":453,"deceased":1,"recovered":150}},"2020-08-01":{"delta":{"confirmed":11,"recovered":38},"total":{"confirmed":464,"deceased":1,"recovered":188}},"2020-08-02":{"delta":{"confirmed":7,"recovered":20},"total":{"confirmed":471,"deceased":1,"recovered":208}},"2020-08-03":{"delta":{"confirmed":16},"total":{"confirmed":487,"deceased":1,"recovered":208}},"2020-08-04":{"delta":{"confirmed":58},"total":{"confirmed":545,"deceased":1,"recovered":208}}}},"North Sikkim":{"dates":{"2020-06-26":{"delta":{"confirmed":1},"total":{"confirmed":1}},"2020-06-27":{"total":{"confirmed":1}},"2020-06-28":{"total":{"confirmed":1}},"2020-06-29":{"total":{"confirmed":1}},"2020-06-30":{"total":{"confirmed":1}},"2020-07-01":{"delta":{"recovered":1},"total":{"confirmed":1,"recovered":1}},"2020-07-02":{"total":{"confirmed":1,"recovered":1}},"2020-07-03":{"total":{"confirmed":1,"recovered":1}},"2020-07-04":{"total":{"confirmed":1,"recovered":1}},"2020-07-05":{"total":{"confirmed":1,"recovered":1}},"2020-07-06":{"total":{"confirmed":1,"recovered":1}},"2020-07-07":{"total":{"confirmed":1,"recovered":1}},"2020-07-08":{"total":{"confirmed":1,"recovered":1}},"2020-07-09":{"total":{"confirmed":1,"recovered":1}},"2020-07-10":{"total":{"confirmed":1,"recovered":1}},"2020-07-11":{"total":{"confirmed":1,"recovered":1}},"2020-07-12":{"total":{"confirmed":1,"recovered":1}},"2020-07-13":{"total":{"confirmed":1,"recovered":1}},"2020-07-14":{"total":{"confirmed":1,"recovered":1}},"2020-07-15":{"total":{"confirmed":1,"recovered":1}},"2020-07-16":{"total":{"confirmed":1,"recovered":1}},"2020-07-17":{"total":{"confirmed":1,"recovered":1}},"2020-07-18":{"total":{"confirmed":1,"recovered":1}},"2020-07-19":{"total":{"confirmed":1,"recovered":1}},"2020-07-20":{"total":{"confirmed":1,"recovered":1}},"2020-07-21":{"total":{"confirmed":1,"recovered":1}},"2020-07-22":{"total":{"confirmed":1,"recovered":1}},"2020-07-23":{"total":{"confirmed":1,"recovered":1}},"2020-07-24":{"total":{"confirmed":1,"recovered":1}},"2020-07-25":{"total":{"confirmed":1,"recovered":1}},"2020-07-26":{"total":{"confirmed":1,"recovered":1}},"2020-07-27":{"total":{"confirmed":1,"recovered":1}},"2020-07-28":{"total":{"confirmed":1,"recovered":1}},"2020-07-29":{"total":{"confirmed":1,"recovered":1}},"2020-07-30":{"total":{"confirmed":1,"recovered":1}},"2020-07-31":{"total":{"confirmed":1,"recovered":1}},"2020-08-01":{"total":{"confirmed":1,"recovered":1}},"2020-08-02":{"total":{"confirmed":1,"recovered":1}},"2020-08-03":{"total":{"confirmed":1,"recovered":1}},"2020-08-04":{"total":{"confirmed":1,"recovered":1}}}},"South Sikkim":{"dates":{"2020-05-23":{"delta":{"confirmed":1},"total":{"confirmed":1}},"2020-05-24":{"total":{"confirmed":1}},"2020-05-25":{"total":{"confirmed":1}},"2020-05-26":{"total":{"confirmed":1}},"2020-05-27":{"total":{"confirmed":1}},"2020-05-28":{"total":{"confirmed":1}},"2020-05-29":{"total":{"confirmed":1}},"2020-05-30":{"total":{"confirmed":1}},"2020-05-31":{"total":{"confirmed":1}},"2020-06-01":{"total":{"confirmed":1}},"2020-06-02":{"total":{"confirmed":1}},"2020-06-03":{"total":{"confirmed":1}},"2020-06-04":{"total":{"confirmed":1}},"2020-06-05":{"total":{"confirmed":1}},"2020-06-06":{"total":{"confirmed":1}},"2020-06-07":{"total":{"confirmed":1}},"2020-06-08":{"total":{"confirmed":1}},"2020-06-09":{"delta":{"confirmed":2},"total":{"confirmed":3}},"2020-06-10":{"total":{"confirmed":3}},"2020-06-11":{"total":{"confirmed":3}},"2020-06-12":{"total":{"confirmed":3}},"2020-06-13":{"delta":{"confirmed":20},"total":{"confirmed":23}},"2020-06-14":{"delta":{"confirmed":4},"total":{"confirmed":27}},"2020-06-15":{"total":{"confirmed":27}},"2020-06-16":{"total":{"confirmed":27}},"2020-06-17":{"total":{"confirmed":27}},"2020-06-18":{"total":{"confirmed":27}},"2020-06-19":{"delta":{"recovered":18},"total":{"confirmed":27,"recovered":18}},"2020-06-20":{"total":{"confirmed":27,"recovered":18}},"2020-06-21":{"delta":{"confirmed":4,"recovered":4},"total":{"confirmed":31,"recovered":22}},"2020-06-22":{"delta":{"recovered":4},"total":{"confirmed":31,"recovered":26}},"2020-06-23":{"total":{"confirmed":31,"recovered":26}},"2020-06-24":{"delta":{"confirmed":4},"total":{"confirmed":35,"recovered":26}},"2020-06-25":{"delta":{"confirmed":1},"total":{"confirmed":36,"recovered":26}},"2020-06-26":{"delta":{"confirmed":2},"total":{"confirmed":38,"recovered":26}},"2020-06-27":{"total":{"confirmed":38,"recovered":26}},"2020-06-28":{"total":{"confirmed":38,"recovered":26}},"2020-06-29":{"total":{"confirmed":38,"recovered":26}},"2020-06-30":{"total":{"confirmed":38,"recovered":26}},"2020-07-01":{"total":{"confirmed":38,"recovered":26}},"2020-07-02":{"total":{"confirmed":38,"recovered":26}},"2020-07-03":{"total":{"confirmed":38,"recovered":26}},"2020-07-04":{"total":{"confirmed":38,"recovered":26}},"2020-07-05":{"total":{"confirmed":38,"recovered":26}},"2020-07-06":{"total":{"confirmed":38,"recovered":26}},"2020-07-07":{"total":{"confirmed":38,"recovered":26}},"2020-07-08":{"total":{"confirmed":38,"recovered":26}},"2020-07-09":{"total":{"confirmed":38,"recovered":26}},"2020-07-10":{"total":{"confirmed":38,"recovered":26}},"2020-07-11":{"total":{"confirmed":38,"recovered":26}},"2020-07-12":{"total":{"confirmed":38,"recovered":26}},"2020-07-13":{"delta":{"confirmed":1},"total":{"confirmed":39,"recovered":26}},"2020-07-14":{"delta":{"confirmed":5},"total":{"confirmed":44,"recovered":26}},"2020-07-15":{"total":{"confirmed":44,"recovered":26}},"2020-07-16":{"total":{"confirmed":44,"recovered":26}},"2020-07-17":{"total":{"confirmed":44,"recovered":26}},"2020-07-18":{"total":{"confirmed":44,"recovered":26}},"2020-07-19":{"total":{"confirmed":44,"recovered":26}},"2020-07-20":{"total":{"confirmed":44,"recovered":26}},"2020-07-21":{"delta":{"confirmed":1},"total":{"confirmed":45,"recovered":26}},"2020-07-22":{"delta":{"confirmed":46},"total":{"confirmed":91,"recovered":26}},"2020-07-23":{"delta":{"recovered":10},"total":{"confirmed":91,"recovered":36}},"2020-07-24":{"delta":{"recovered":15},"total":{"confirmed":91,"recovered":51}},"2020-07-25":{"delta":{"confirmed":22,"recovered":5},"total":{"confirmed":113,"recovered":56}},"2020-07-26":{"delta":{"confirmed":46,"recovered":5},"total":{"confirmed":159,"recovered":61}},"2020-07-27":{"total":{"confirmed":159,"recovered":61}},"2020-07-28":{"delta":{"confirmed":16},"total":{"confirmed":175,"recovered":61}},"2020-07-29":{"delta":{"confirmed":-16},"total":{"confirmed":159,"recovered":61}},"2020-07-30":{"delta":{"confirmed":-16,"recovered":4},"total":{"confirmed":143,"recovered":65}},"2020-07-31":{"total":{"confirmed":143,"recovered":65}},"2020-08-01":{"total":{"confirmed":143,"recovered":65}},"2020-08-02":{"delta":{"confirmed":1},"total":{"confirmed":144,"recovered":65}},"2020-08-03":{"delta":{"confirmed":14},"total":{"confirmed":158,"recovered":65}},"2020-08-04":{"delta":{"confirmed":37},"total":{"confirmed":195,"recovered":65}}}},"Unknown":{"dates":{"2020-06-09":{"delta":{"confirmed":3},"total":{"confirmed":3}},"2020-06-10":{"total":{"confirmed":3}},"2020-06-11":{"total":{"confirmed":3}},"2020-06-12":{"delta":{"confirmed":36},"total":{"confirmed":39}},"2020-06-13":{"delta":{"confirmed":-39}},"2020-06-14":{"delta":{"confirmed":1},"total":{"confirmed":1}},"2020-06-15":{"total":{"confirmed":1}},"2020-06-16":{"total":{"confirmed":1}},"2020-06-17":{"total":{"confirmed":1}},"2020-06-18":{"total":{"confirmed":1}},"2020-06-19":{"total":{"confirmed":1}},"2020-06-20":{"total":{"confirmed":1}},"2020-06-21":{"total":{"confirmed":1}},"2020-06-22":{"total":{"confirmed":1}},"2020-06-23":{"delta":{"confirmed":1},"total":{"confirmed":2}},"2020-06-24":{"total":{"confirmed":2}},"2020-06-25":{"total":{"confirmed":2}},"2020-06-26":{"delta":{"confirmed":-2}},"2020-07-01":{"delta":{"recovered":1},"total":{"recovered":1}},"2020-07-02":{"delta":{"recovered":-1}},"2020-07-03":{"delta":{"confirmed":1},"total":{"confirmed":1}},"2020-07-04":{"delta":{"confirmed":-1}},"2020-07-27":{"delta":{"confirmed":10,"recovered":27},"total":{"confirmed":10,"recovered":27}},"2020-07-28":{"delta":{"recovered":12},"total":{"confirmed":10,"recovered":39}},"2020-07-29":{"delta":{"confirmed":-10,"recovered":-39}},"2020-08-03":{"delta":{"recovered":8},"total":{"recovered":8}},"2020-08-04":{"delta":{"recovered":2},"total":{"recovered":10}}}},"West Sikkim":{"dates":{"2020-06-06":{"delta":{"confirmed":3},"total":{"confirmed":3}},"2020-06-07":{"total":{"confirmed":3}},"2020-06-08":{"total":{"confirmed":3}},"2020-06-09":{"delta":{"confirmed":1},"total":{"confirmed":4}},"2020-06-10":{"total":{"confirmed":4}},"2020-06-11":{"total":{"confirmed":4}},"2020-06-12":{"total":{"confirmed":4}},"2020-06-13":{"delta":{"confirmed":9},"total":{"confirmed":13}},"2020-06-14":{"delta":{"confirmed":7},"total":{"confirmed":20}},"2020-06-15":{"total":{"confirmed":20}},"2020-06-16":{"total":{"confirmed":20}},"2020-06-17":{"delta":{"confirmed":1},"total":{"confirmed":21}},"2020-06-18":{"total":{"confirmed":21}},"2020-06-19":{"delta":{"recovered":1},"total":{"confirmed":21,"recovered":1}},"2020-06-20":{"total":{"confirmed":21,"recovered":1}},"2020-06-21":{"total":{"confirmed":21,"recovered":1}},"2020-06-22":{"total":{"confirmed":21,"recovered":1}},"2020-06-23":{"total":{"confirmed":21,"recovered":1}},"2020-06-24":{"delta":{"recovered":9},"total":{"confirmed":21,"recovered":10}},"2020-06-25":{"total":{"confirmed":21,"recovered":10}},"2020-06-26":{"total":{"confirmed":21,"recovered":10}},"2020-06-27":{"delta":{"recovered":1},"total":{"confirmed":21,"recovered":11}},"2020-06-28":{"total":{"confirmed":21,"recovered":11}},"2020-06-29":{"total":{"confirmed":21,"recovered":11}},"2020-06-30":{"delta":{"recovered":1},"total":{"confirmed":21,"recovered":12}},"2020-07-01":{"total":{"confirmed":21,"recovered":12}},"2020-07-02":{"delta":{"recovered":-1},"total":{"confirmed":21,"recovered":11}},"2020-07-03":{"total":{"confirmed":21,"recovered":11}},"2020-07-04":{"total":{"confirmed":21,"recovered":11}},"2020-07-05":{"total":{"confirmed":21,"recovered":11}},"2020-07-06":{"total":{"confirmed":21,"recovered":11}},"2020-07-07":{"total":{"confirmed":21,"recovered":11}},"2020-07-08":{"total":{"confirmed":21,"recovered":11}},"2020-07-09":{"total":{"confirmed":21,"recovered":11}},"2020-07-10":{"total":{"confirmed":21,"recovered":11}},"2020-07-11":{"total":{"confirmed":21,"recovered":11}},"2020-07-12":{"total":{"confirmed":21,"recovered":11}},"2020-07-13":{"total":{"confirmed":21,"recovered":11}},"2020-07-14":{"delta":{"confirmed":1},"total":{"confirmed":22,"recovered":11}},"2020-07-15":{"total":{"confirmed":22,"recovered":11}},"2020-07-16":{"total":{"confirmed":22,"recovered":11}},"2020-07-17":{"delta":{"confirmed":7},"total":{"confirmed":29,"recovered":11}},"2020-07-18":{"total":{"confirmed":29,"recovered":11}},"2020-07-19":{"total":{"confirmed":29,"recovered":11}},"2020-07-20":{"total":{"confirmed":29,"recovered":11}},"2020-07-21":{"total":{"confirmed":29,"recovered":11}},"2020-07-22":{"delta":{"confirmed":1},"total":{"confirmed":30,"recovered":11}},"2020-07-23":{"delta":{"confirmed":3},"total":{"confirmed":33,"recovered":11}},"2020-07-24":{"delta":{"confirmed":6},"total":{"confirmed":39,"recovered":11}},"2020-07-25":{"total":{"confirmed":39,"recovered":11}},"2020-07-26":{"total":{"confirmed":39,"recovered":11}},"2020-07-27":{"total":{"confirmed":39,"recovered":11}},"2020-07-28":{"total":{"confirmed":39,"recovered":11}},"2020-07-29":{"total":{"confirmed":39,"recovered":11}},"2020-07-30":{"delta":{"confirmed":2,"recovered":4},"total":{"confirmed":41,"recovered":15}},"2020-07-31":{"delta":{"confirmed":1},"total":{"confirmed":42,"recovered":15}},"2020-08-01":{"total":{"confirmed":42,"recovered":15}},"2020-08-02":{"total":{"confirmed":42,"recovered":15}},"2020-08-03":{"total":{"confirmed":42,"recovered":15}},"2020-08-04":{"total":{"confirmed":42,"recovered":15}}}}}}}